{
  "owner": {
    "subscriptions_url": "https://api.github.com/users/csurgotamas/subscriptions",
    "received_events_url": "https://api.github.com/users/csurgotamas/received_events",
    "events_url": "https://api.github.com/users/csurgotamas/events{/privacy}",
    "gists_url": "https://api.github.com/users/csurgotamas/gists{/gist_id}",
    "url": "https://api.github.com/users/csurgotamas",
    "repos_url": "https://api.github.com/users/csurgotamas/repos",
    "login": "csurgotamas",
    "html_url": "https://github.com/csurgotamas",
    "organizations_url": "https://api.github.com/users/csurgotamas/orgs",
    "following_url": "https://api.github.com/users/csurgotamas/following{/other_user}",
    "type": "User",
    "avatar_url": "https://avatars2.githubusercontent.com/u/1508054?v=3",
    "gravatar_id": "",
    "site_admin": false,
    "id": 1508054,
    "followers_url": "https://api.github.com/users/csurgotamas/followers",
    "starred_url": "https://api.github.com/users/csurgotamas/starred{/owner}{/repo}"
  },
  "events_url": "https://api.github.com/repos/csurgotamas/Evilstore/events",
  "network_count": 1,
  "milestones_url": "https://api.github.com/repos/csurgotamas/Evilstore/milestones{/number}",
  "created_at": "2012-06-06T17:48:28Z",
  "compare_url": "https://api.github.com/repos/csurgotamas/Evilstore/compare/{base}...{head}",
  "deployments_url": "https://api.github.com/repos/csurgotamas/Evilstore/deployments",
  "svn_url": "https://github.com/csurgotamas/Evilstore",
  "trees_url": "https://api.github.com/repos/csurgotamas/Evilstore/git/trees{/sha}",
  "html_url": "https://github.com/csurgotamas/Evilstore",
  "forks_count": 1,
  "has_downloads": true,
  "watchers": 1,
  "watchers_count": 1,
  "has_pages": false,
  "stargazers_url": "https://api.github.com/repos/csurgotamas/Evilstore/stargazers",
  "mirror_url": null,
  "commits_url": "https://api.github.com/repos/csurgotamas/Evilstore/commits{/sha}",
  "archive_url": "https://api.github.com/repos/csurgotamas/Evilstore/{archive_format}{/ref}",
  "full_name": "csurgotamas/Evilstore",
  "git_commits_url": "https://api.github.com/repos/csurgotamas/Evilstore/git/commits{/sha}",
  "clone_url": "https://github.com/csurgotamas/Evilstore.git",
  "contents_url": "https://api.github.com/repos/csurgotamas/Evilstore/contents/{+path}",
  "merges_url": "https://api.github.com/repos/csurgotamas/Evilstore/merges",
  "fork": false,
  "name": "Evilstore",
  "issue_comment_url": "https://api.github.com/repos/csurgotamas/Evilstore/issues/comments{/number}",
  "stargazers_count": 1,
  "size": 24500,
  "branches_url": "https://api.github.com/repos/csurgotamas/Evilstore/branches{/branch}",
  "has_issues": true,
  "releases_url": "https://api.github.com/repos/csurgotamas/Evilstore/releases{/id}",
  "id": 4575855,
  "tags_url": "https://api.github.com/repos/csurgotamas/Evilstore/tags",
  "permissions": {
    "admin": false,
    "push": false,
    "pull": true
  },
  "ssh_url": "git@github.com:csurgotamas/Evilstore.git",
  "comments_url": "https://api.github.com/repos/csurgotamas/Evilstore/comments{/number}",
  "git_refs_url": "https://api.github.com/repos/csurgotamas/Evilstore/git/refs{/sha}",
  "keys_url": "https://api.github.com/repos/csurgotamas/Evilstore/keys{/key_id}",
  "forks": 1,
  "open_issues": 0,
  "statuses_url": "https://api.github.com/repos/csurgotamas/Evilstore/statuses/{sha}",
  "contributors_url": "https://api.github.com/repos/csurgotamas/Evilstore/contributors",
  "blobs_url": "https://api.github.com/repos/csurgotamas/Evilstore/git/blobs{/sha}",
  "forks_url": "https://api.github.com/repos/csurgotamas/Evilstore/forks",
  "assignees_url": "https://api.github.com/repos/csurgotamas/Evilstore/assignees{/user}",
  "open_issues_count": 0,
  "labels_url": "https://api.github.com/repos/csurgotamas/Evilstore/labels{/name}",
  "pushed_at": "2012-06-07T14:11:18Z",
  "private": false,
  "languages_url": "https://api.github.com/repos/csurgotamas/Evilstore/languages",
  "description": "A service oriented online application store developed in model driven paradigm.",
  "subscribers_count": 1,
  "has_wiki": true,
  "default_branch": "master",
  "notifications_url": "https://api.github.com/repos/csurgotamas/Evilstore/notifications{?since,all,participating}",
  "updated_at": "2014-02-06T19:01:23Z",
  "issues_url": "https://api.github.com/repos/csurgotamas/Evilstore/issues{/number}",
  "teams_url": "https://api.github.com/repos/csurgotamas/Evilstore/teams",
  "url": "https://api.github.com/repos/csurgotamas/Evilstore",
  "language": "Java",
  "collaborators_url": "https://api.github.com/repos/csurgotamas/Evilstore/collaborators{/collaborator}",
  "downloads_url": "https://api.github.com/repos/csurgotamas/Evilstore/downloads",
  "git_tags_url": "https://api.github.com/repos/csurgotamas/Evilstore/git/tags{/sha}",
  "issue_events_url": "https://api.github.com/repos/csurgotamas/Evilstore/issues/events{/number}",
  "subscription_url": "https://api.github.com/repos/csurgotamas/Evilstore/subscription",
  "git_url": "git://github.com/csurgotamas/Evilstore.git",
  "subscribers_url": "https://api.github.com/repos/csurgotamas/Evilstore/subscribers",
  "homepage": null,
  "pulls_url": "https://api.github.com/repos/csurgotamas/Evilstore/pulls{/number}",
  "hooks_url": "https://api.github.com/repos/csurgotamas/Evilstore/hooks"
}