[
  {
    "operations": {},
    "body": "'UTF-8'",
    "type": "FileCharset",
    "constructs": {"StringLiteralExpImpl": 1},
    "properties": []
  },
  {
    "operations": {"+": 1},
    "body": "minidroneProgram.name.+('.c')",
    "type": "FileUrl",
    "constructs": {
      "OperationCallExpImpl": 1,
      "VariableExpImpl": 1,
      "StringLiteralExpImpl": 1,
      "PropertyCallExpImpl": 1
    },
    "properties": ["name"]
  },
  {
    "operations": {},
    "body": "minidroneProgram.name",
    "type": "TemplateExpression",
    "constructs": {
      "VariableExpImpl": 1,
      "PropertyCallExpImpl": 1
    },
    "properties": ["name"]
  },
  {
    "operations": {},
    "body": "'\n'",
    "type": "ForEach",
    "constructs": {"StringLiteralExpImpl": 1},
    "properties": []
  },
  {
    "operations": {},
    "body": "minidroneProgram.instructions",
    "type": "ForIter",
    "constructs": {
      "VariableExpImpl": 1,
      "PropertyCallExpImpl": 1
    },
    "properties": ["instructions"]
  },
  {
    "operations": {"oclIsTypeOf": 1},
    "body": "it.oclIsTypeOf(minidrone::Go)",
    "type": "IfExpression",
    "constructs": {
      "OperationCallExpImpl": 1,
      "VariableExpImpl": 1,
      "TypeExpImpl": 1
    },
    "properties": []
  },
  {
    "operations": {"oclAsType": 1},
    "body": "it.oclAsType(minidrone::Go).distance",
    "type": "TemplateExpression",
    "constructs": {
      "OperationCallExpImpl": 1,
      "VariableExpImpl": 1,
      "TypeExpImpl": 1,
      "PropertyCallExpImpl": 1
    },
    "properties": ["distance"]
  },
  {
    "operations": {"oclIsTypeOf": 1},
    "body": "it.oclIsTypeOf(minidrone::Turn)",
    "type": "IfExpression",
    "constructs": {
      "OperationCallExpImpl": 1,
      "VariableExpImpl": 1,
      "TypeExpImpl": 1
    },
    "properties": []
  },
  {
    "operations": {"oclAsType": 1},
    "body": "it.oclAsType(minidrone::Turn).angle",
    "type": "TemplateExpression",
    "constructs": {
      "VariableExpImpl": 1,
      "OperationCallExpImpl": 1,
      "TypeExpImpl": 1,
      "PropertyCallExpImpl": 1
    },
    "properties": ["angle"]
  },
  {
    "operations": {"oclIsTypeOf": 1},
    "body": "it.oclIsTypeOf(minidrone::Jump)",
    "type": "IfExpression",
    "constructs": {
      "VariableExpImpl": 1,
      "OperationCallExpImpl": 1,
      "TypeExpImpl": 1
    },
    "properties": []
  },
  {
    "operations": {"oclAsType": 1},
    "body": "it.oclAsType(minidrone::Jump).jumpType",
    "type": "TemplateExpression",
    "constructs": {
      "OperationCallExpImpl": 1,
      "VariableExpImpl": 1,
      "TypeExpImpl": 1,
      "PropertyCallExpImpl": 1
    },
    "properties": ["jumpType"]
  }
]
