[
  {
    "operations": {},
    "body": "anActivityNode",
    "type": "QueryInvocationArgument",
    "constructs": {"VariableExpImpl": 1},
    "properties": []
  },
  {
    "operations": {"eClass": 1},
    "body": "anActivityNode.eClass().name",
    "type": "TemplateExpression",
    "constructs": {
      "VariableExpImpl": 1,
      "OperationCallExpImpl": 1,
      "PropertyCallExpImpl": 1
    },
    "properties": ["name"]
  },
  {
    "operations": {},
    "body": "anActivityNode",
    "type": "QueryInvocationArgument",
    "constructs": {"VariableExpImpl": 1},
    "properties": []
  },
  {
    "operations": {},
    "body": "anActivityNode.name",
    "type": "TemplateExpression",
    "constructs": {
      "VariableExpImpl": 1,
      "PropertyCallExpImpl": 1
    },
    "properties": ["name"]
  },
  {
    "operations": {},
    "body": "anActivityNode",
    "type": "QueryInvocationArgument",
    "constructs": {"VariableExpImpl": 1},
    "properties": []
  },
  {
    "operations": {"oclAsType": 1},
    "body": "anActivityNode.activity.oclAsType(uml::NamedElement)",
    "type": "QueryInvocationArgument",
    "constructs": {
      "VariableExpImpl": 1,
      "OperationCallExpImpl": 1,
      "TypeExpImpl": 1,
      "PropertyCallExpImpl": 1
    },
    "properties": ["activity"]
  },
  {
    "operations": {},
    "body": "anActivityNode",
    "type": "TemplateInvocationArgument",
    "constructs": {"VariableExpImpl": 1},
    "properties": []
  },
  {
    "operations": {"oclIsKindOf": 1},
    "body": "self.oclIsKindOf(uml::CallBehaviorAction)",
    "type": "TemplateGuard",
    "constructs": {
      "OperationCallExpImpl": 1,
      "VariableExpImpl": 1,
      "TypeExpImpl": 1
    },
    "properties": []
  },
  {
    "operations": {},
    "body": "anActivityNode.name",
    "type": "TemplateExpression",
    "constructs": {
      "VariableExpImpl": 1,
      "PropertyCallExpImpl": 1
    },
    "properties": ["name"]
  },
  {
    "operations": {},
    "body": "anActivityNode",
    "type": "QueryInvocationArgument",
    "constructs": {"VariableExpImpl": 1},
    "properties": []
  },
  {
    "operations": {"oclAsType": 2},
    "body": "anActivityNode.oclAsType(uml::CallBehaviorAction).behavior.oclAsType(uml::NamedElement)",
    "type": "QueryInvocationArgument",
    "constructs": {
      "OperationCallExpImpl": 2,
      "VariableExpImpl": 1,
      "TypeExpImpl": 2,
      "PropertyCallExpImpl": 1
    },
    "properties": ["behavior"]
  },
  {
    "operations": {},
    "body": "anActivityNode",
    "type": "QueryInvocationArgument",
    "constructs": {"VariableExpImpl": 1},
    "properties": []
  },
  {
    "operations": {"oclAsType": 1},
    "body": "anActivityNode.oclAsType(uml::CallBehaviorAction).input->collect(temp1 : InputPin | generatePin(temp1))",
    "type": "TemplateExpression",
    "constructs": {
      "IteratorExpImpl": 1,
      "VariableExpImpl": 2,
      "OperationCallExpImpl": 1,
      "TemplateInvocationSpec": 1,
      "TypeExpImpl": 1,
      "PropertyCallExpImpl": 1
    },
    "properties": ["input"]
  },
  {
    "operations": {"oclAsType": 1},
    "body": "anActivityNode.oclAsType(uml::CallBehaviorAction).output->collect(temp1 : OutputPin | generatePin(temp1))",
    "type": "TemplateExpression",
    "constructs": {
      "IteratorExpImpl": 1,
      "VariableExpImpl": 2,
      "OperationCallExpImpl": 1,
      "TemplateInvocationSpec": 1,
      "TypeExpImpl": 1,
      "PropertyCallExpImpl": 1
    },
    "properties": ["output"]
  },
  {
    "operations": {"oclIsKindOf": 1},
    "body": "self.oclIsKindOf(uml::CallOperationAction)",
    "type": "TemplateGuard",
    "constructs": {
      "OperationCallExpImpl": 1,
      "VariableExpImpl": 1,
      "TypeExpImpl": 1
    },
    "properties": []
  },
  {
    "operations": {},
    "body": "anActivityNode.name",
    "type": "TemplateExpression",
    "constructs": {
      "VariableExpImpl": 1,
      "PropertyCallExpImpl": 1
    },
    "properties": ["name"]
  },
  {
    "operations": {"oclAsType": 1},
    "body": "anActivityNode.oclAsType(uml::CallOperationAction).input->collect(temp1 : InputPin | generatePin(temp1))",
    "type": "TemplateExpression",
    "constructs": {
      "IteratorExpImpl": 1,
      "OperationCallExpImpl": 1,
      "VariableExpImpl": 2,
      "TemplateInvocationSpec": 1,
      "TypeExpImpl": 1,
      "PropertyCallExpImpl": 1
    },
    "properties": ["input"]
  },
  {
    "operations": {"oclAsType": 1},
    "body": "anActivityNode.oclAsType(uml::CallOperationAction).output->collect(temp1 : OutputPin | generatePin(temp1))",
    "type": "TemplateExpression",
    "constructs": {
      "IteratorExpImpl": 1,
      "VariableExpImpl": 2,
      "OperationCallExpImpl": 1,
      "TemplateInvocationSpec": 1,
      "TypeExpImpl": 1,
      "PropertyCallExpImpl": 1
    },
    "properties": ["output"]
  },
  {
    "operations": {"oclAsType": 1},
    "body": "anActivityNode.oclAsType(uml::CallOperationAction).operation",
    "type": "TemplateInvocationArgument",
    "constructs": {
      "OperationCallExpImpl": 1,
      "VariableExpImpl": 1,
      "TypeExpImpl": 1,
      "PropertyCallExpImpl": 1
    },
    "properties": ["operation"]
  },
  {
    "operations": {},
    "body": "pin",
    "type": "QueryInvocationArgument",
    "constructs": {"VariableExpImpl": 1},
    "properties": []
  },
  {
    "operations": {"eClass": 1},
    "body": "pin.eClass().name",
    "type": "TemplateExpression",
    "constructs": {
      "OperationCallExpImpl": 1,
      "VariableExpImpl": 1,
      "PropertyCallExpImpl": 1
    },
    "properties": ["name"]
  },
  {
    "operations": {},
    "body": "pin",
    "type": "QueryInvocationArgument",
    "constructs": {"VariableExpImpl": 1},
    "properties": []
  },
  {
    "operations": {},
    "body": "pin.name",
    "type": "TemplateExpression",
    "constructs": {
      "VariableExpImpl": 1,
      "PropertyCallExpImpl": 1
    },
    "properties": ["name"]
  },
  {
    "operations": {},
    "body": "operation",
    "type": "QueryInvocationArgument",
    "constructs": {"VariableExpImpl": 1},
    "properties": []
  },
  {
    "operations": {},
    "body": "operation",
    "type": "QueryInvocationArgument",
    "constructs": {"VariableExpImpl": 1},
    "properties": []
  },
  {
    "operations": {},
    "body": "operation.name",
    "type": "TemplateExpression",
    "constructs": {
      "VariableExpImpl": 1,
      "PropertyCallExpImpl": 1
    },
    "properties": ["name"]
  },
  {
    "operations": {"oclAsType": 1},
    "body": "anActivityNode.activity.oclAsType(uml::NamedElement)",
    "type": "QueryInvocationArgument",
    "constructs": {
      "VariableExpImpl": 1,
      "OperationCallExpImpl": 1,
      "TypeExpImpl": 1,
      "PropertyCallExpImpl": 1
    },
    "properties": ["activity"]
  },
  {
    "operations": {},
    "body": "anActivityNode",
    "type": "QueryInvocationArgument",
    "constructs": {"VariableExpImpl": 1},
    "properties": []
  },
  {
    "operations": {},
    "body": "anActivityNode",
    "type": "TemplateInvocationArgument",
    "constructs": {"VariableExpImpl": 1},
    "properties": []
  },
  {
    "operations": {"oclIsKindOf": 1},
    "body": "self.oclIsKindOf(uml::ActivityParameterNode)",
    "type": "TemplateGuard",
    "constructs": {
      "OperationCallExpImpl": 1,
      "VariableExpImpl": 1,
      "TypeExpImpl": 1
    },
    "properties": []
  },
  {
    "operations": {},
    "body": "anActivityNode",
    "type": "QueryInvocationArgument",
    "constructs": {"VariableExpImpl": 1},
    "properties": []
  },
  {
    "operations": {"oclAsType": 1},
    "body": "anActivityNode.oclAsType(uml::ActivityParameterNode).parameter",
    "type": "QueryInvocationArgument",
    "constructs": {
      "OperationCallExpImpl": 1,
      "VariableExpImpl": 1,
      "TypeExpImpl": 1,
      "PropertyCallExpImpl": 1
    },
    "properties": ["parameter"]
  },
  {
    "operations": {"oclIsKindOf": 1},
    "body": "self.oclIsKindOf(uml::CallBehaviorAction)",
    "type": "TemplateGuard",
    "constructs": {
      "OperationCallExpImpl": 1,
      "VariableExpImpl": 1,
      "TypeExpImpl": 1
    },
    "properties": []
  },
  {
    "operations": {},
    "body": "anActivityNode",
    "type": "QueryInvocationArgument",
    "constructs": {"VariableExpImpl": 1},
    "properties": []
  },
  {
    "operations": {"oclAsType": 1},
    "body": "anActivityNode.oclAsType(uml::CallBehaviorAction).behavior",
    "type": "QueryInvocationArgument",
    "constructs": {
      "VariableExpImpl": 1,
      "OperationCallExpImpl": 1,
      "TypeExpImpl": 1,
      "PropertyCallExpImpl": 1
    },
    "properties": ["behavior"]
  },
  {
    "operations": {"oclAsType": 1},
    "body": "anActivityNode.oclAsType(uml::CallBehaviorAction).input->collect(temp1 : InputPin | initializePin(temp1))",
    "type": "TemplateExpression",
    "constructs": {
      "IteratorExpImpl": 1,
      "OperationCallExpImpl": 1,
      "VariableExpImpl": 2,
      "TemplateInvocationSpec": 1,
      "TypeExpImpl": 1,
      "PropertyCallExpImpl": 1
    },
    "properties": ["input"]
  },
  {
    "operations": {"oclAsType": 1},
    "body": "anActivityNode.oclAsType(uml::CallBehaviorAction).output->collect(temp1 : OutputPin | initializePin(temp1))",
    "type": "TemplateExpression",
    "constructs": {
      "IteratorExpImpl": 1,
      "VariableExpImpl": 2,
      "OperationCallExpImpl": 1,
      "TemplateInvocationSpec": 1,
      "TypeExpImpl": 1,
      "PropertyCallExpImpl": 1
    },
    "properties": ["output"]
  },
  {
    "operations": {"oclIsKindOf": 1},
    "body": "self.oclIsKindOf(uml::CallOperationAction)",
    "type": "TemplateGuard",
    "constructs": {
      "OperationCallExpImpl": 1,
      "VariableExpImpl": 1,
      "TypeExpImpl": 1
    },
    "properties": []
  },
  {
    "operations": {},
    "body": "anActivityNode",
    "type": "QueryInvocationArgument",
    "constructs": {"VariableExpImpl": 1},
    "properties": []
  },
  {
    "operations": {"oclAsType": 1},
    "body": "anActivityNode.oclAsType(uml::CallOperationAction).operation",
    "type": "QueryInvocationArgument",
    "constructs": {
      "OperationCallExpImpl": 1,
      "VariableExpImpl": 1,
      "TypeExpImpl": 1,
      "PropertyCallExpImpl": 1
    },
    "properties": ["operation"]
  },
  {
    "operations": {"oclAsType": 1},
    "body": "anActivityNode.oclAsType(uml::CallOperationAction).input->collect(temp1 : InputPin | initializePin(temp1))",
    "type": "TemplateExpression",
    "constructs": {
      "IteratorExpImpl": 1,
      "OperationCallExpImpl": 1,
      "VariableExpImpl": 2,
      "TemplateInvocationSpec": 1,
      "TypeExpImpl": 1,
      "PropertyCallExpImpl": 1
    },
    "properties": ["input"]
  },
  {
    "operations": {"oclAsType": 1},
    "body": "anActivityNode.oclAsType(uml::CallOperationAction).output->collect(temp1 : OutputPin | initializePin(temp1))",
    "type": "TemplateExpression",
    "constructs": {
      "IteratorExpImpl": 1,
      "OperationCallExpImpl": 1,
      "VariableExpImpl": 2,
      "TemplateInvocationSpec": 1,
      "TypeExpImpl": 1,
      "PropertyCallExpImpl": 1
    },
    "properties": ["output"]
  },
  {
    "operations": {},
    "body": "anActivityNode",
    "type": "QueryInvocationArgument",
    "constructs": {"VariableExpImpl": 1},
    "properties": []
  },
  {
    "operations": {"oclAsType": 1},
    "body": "anActivityNode.oclAsType(uml::CallOperationAction).target",
    "type": "QueryInvocationArgument",
    "constructs": {
      "VariableExpImpl": 1,
      "OperationCallExpImpl": 1,
      "TypeExpImpl": 1,
      "PropertyCallExpImpl": 1
    },
    "properties": ["target"]
  },
  {
    "operations": {"oclIsKindOf": 1},
    "body": "self.oclIsKindOf(uml::DecisionNode)",
    "type": "TemplateGuard",
    "constructs": {
      "VariableExpImpl": 1,
      "OperationCallExpImpl": 1,
      "TypeExpImpl": 1
    },
    "properties": []
  },
  {
    "operations": {
      "not": 1,
      "oclIsUndefined": 1,
      "oclAsType": 1
    },
    "body": "anActivityNode.oclAsType(uml::DecisionNode).decisionInput.oclIsUndefined().not()",
    "type": "IfExpression",
    "constructs": {
      "OperationCallExpImpl": 3,
      "VariableExpImpl": 1,
      "TypeExpImpl": 1,
      "PropertyCallExpImpl": 1
    },
    "properties": ["decisionInput"]
  },
  {
    "operations": {},
    "body": "anActivityNode",
    "type": "QueryInvocationArgument",
    "constructs": {"VariableExpImpl": 1},
    "properties": []
  },
  {
    "operations": {"oclAsType": 1},
    "body": "anActivityNode.oclAsType(uml::DecisionNode).decisionInput",
    "type": "QueryInvocationArgument",
    "constructs": {
      "VariableExpImpl": 1,
      "OperationCallExpImpl": 1,
      "TypeExpImpl": 1,
      "PropertyCallExpImpl": 1
    },
    "properties": ["decisionInput"]
  },
  {
    "operations": {"oclIsKindOf": 1},
    "body": "pin.oclIsKindOf(uml::InputPin)",
    "type": "IfExpression",
    "constructs": {
      "OperationCallExpImpl": 1,
      "VariableExpImpl": 1,
      "TypeExpImpl": 1
    },
    "properties": []
  },
  {
    "operations": {"oclAsType": 1},
    "body": "pin.owner.oclAsType(uml::NamedElement)",
    "type": "QueryInvocationArgument",
    "constructs": {
      "VariableExpImpl": 1,
      "OperationCallExpImpl": 1,
      "TypeExpImpl": 1,
      "PropertyCallExpImpl": 1
    },
    "properties": ["owner"]
  },
  {
    "operations": {},
    "body": "pin",
    "type": "QueryInvocationArgument",
    "constructs": {"VariableExpImpl": 1},
    "properties": []
  },
  {
    "operations": {"oclAsType": 1},
    "body": "pin.owner.oclAsType(uml::NamedElement)",
    "type": "QueryInvocationArgument",
    "constructs": {
      "VariableExpImpl": 1,
      "OperationCallExpImpl": 1,
      "TypeExpImpl": 1,
      "PropertyCallExpImpl": 1
    },
    "properties": ["owner"]
  },
  {
    "operations": {},
    "body": "pin",
    "type": "QueryInvocationArgument",
    "constructs": {"VariableExpImpl": 1},
    "properties": []
  }
]
