[
  {
    "operations": {},
    "body": "'ASCII'",
    "type": "FileCharset",
    "constructs": {"StringLiteralExpImpl": 1},
    "properties": []
  },
  {
    "operations": {},
    "body": "aRteSource.fileName",
    "type": "FileUrl",
    "constructs": {
      "VariableExpImpl": 1,
      "PropertyCallExpImpl": 1
    },
    "properties": ["fileName"]
  },
  {
    "operations": {},
    "body": "aRteSource",
    "type": "TemplateInvocationArgument",
    "constructs": {"VariableExpImpl": 1},
    "properties": []
  },
  {
    "operations": {},
    "body": "aRteSource",
    "type": "TemplateInvocationArgument",
    "constructs": {"VariableExpImpl": 1},
    "properties": []
  },
  {
    "operations": {},
    "body": "aRteSource",
    "type": "TemplateInvocationArgument",
    "constructs": {"VariableExpImpl": 1},
    "properties": []
  },
  {
    "operations": {},
    "body": "aRteSource",
    "type": "TemplateInvocationArgument",
    "constructs": {"VariableExpImpl": 1},
    "properties": []
  },
  {
    "operations": {},
    "body": "aRteSource",
    "type": "TemplateInvocationArgument",
    "constructs": {"VariableExpImpl": 1},
    "properties": []
  },
  {
    "operations": {},
    "body": "aRteSource",
    "type": "TemplateInvocationArgument",
    "constructs": {"VariableExpImpl": 1},
    "properties": []
  },
  {
    "operations": {},
    "body": "aRteSource",
    "type": "TemplateInvocationArgument",
    "constructs": {"VariableExpImpl": 1},
    "properties": []
  },
  {
    "operations": {},
    "body": "aRteSource",
    "type": "TemplateInvocationArgument",
    "constructs": {"VariableExpImpl": 1},
    "properties": []
  },
  {
    "operations": {},
    "body": "aRteSource",
    "type": "TemplateInvocationArgument",
    "constructs": {"VariableExpImpl": 1},
    "properties": []
  },
  {
    "operations": {},
    "body": "aRteSource",
    "type": "TemplateInvocationArgument",
    "constructs": {"VariableExpImpl": 1},
    "properties": []
  },
  {
    "operations": {},
    "body": "aRteSource",
    "type": "TemplateInvocationArgument",
    "constructs": {"VariableExpImpl": 1},
    "properties": []
  },
  {
    "operations": {},
    "body": "aRteSource",
    "type": "TemplateInvocationArgument",
    "constructs": {"VariableExpImpl": 1},
    "properties": []
  },
  {
    "operations": {},
    "body": "aRteSource",
    "type": "TemplateInvocationArgument",
    "constructs": {"VariableExpImpl": 1},
    "properties": []
  },
  {
    "operations": {},
    "body": "aRteSource",
    "type": "TemplateInvocationArgument",
    "constructs": {"VariableExpImpl": 1},
    "properties": []
  },
  {
    "operations": {},
    "body": "aRteSource",
    "type": "TemplateInvocationArgument",
    "constructs": {"VariableExpImpl": 1},
    "properties": []
  },
  {
    "operations": {},
    "body": "aRteSource",
    "type": "TemplateInvocationArgument",
    "constructs": {"VariableExpImpl": 1},
    "properties": []
  },
  {
    "operations": {},
    "body": "aRteSource",
    "type": "TemplateInvocationArgument",
    "constructs": {"VariableExpImpl": 1},
    "properties": []
  },
  {
    "operations": {},
    "body": "aRteSource.sourceMacro",
    "type": "ForIter",
    "constructs": {
      "VariableExpImpl": 1,
      "PropertyCallExpImpl": 1
    },
    "properties": ["sourceMacro"]
  },
  {
    "operations": {},
    "body": "aMacro",
    "type": "TemplateInvocationArgument",
    "constructs": {"VariableExpImpl": 1},
    "properties": []
  },
  {
    "operations": {},
    "body": "aRteSource.globalVariableGroup",
    "type": "ForIter",
    "constructs": {
      "VariableExpImpl": 1,
      "PropertyCallExpImpl": 1
    },
    "properties": ["globalVariableGroup"]
  },
  {
    "operations": {},
    "body": "aGroup.memoryMapping",
    "type": "TemplateInvocationArgument",
    "constructs": {
      "VariableExpImpl": 1,
      "PropertyCallExpImpl": 1
    },
    "properties": ["memoryMapping"]
  },
  {
    "operations": {},
    "body": "aGroup.globalVariable",
    "type": "ForIter",
    "constructs": {
      "VariableExpImpl": 1,
      "PropertyCallExpImpl": 1
    },
    "properties": ["globalVariable"]
  },
  {
    "operations": {},
    "body": "aGlobalVariable",
    "type": "TemplateInvocationArgument",
    "constructs": {"VariableExpImpl": 1},
    "properties": []
  },
  {
    "operations": {},
    "body": "aGroup.memoryMapping",
    "type": "TemplateInvocationArgument",
    "constructs": {
      "VariableExpImpl": 1,
      "PropertyCallExpImpl": 1
    },
    "properties": ["memoryMapping"]
  },
  {
    "operations": {"trim": 1},
    "body": "self.trim()",
    "type": "TemplatePost",
    "constructs": {
      "OperationCallExpImpl": 1,
      "VariableExpImpl": 1
    },
    "properties": []
  },
  {
    "operations": {},
    "body": "aGlobalVariable.type",
    "type": "TemplateInvocationArgument",
    "constructs": {
      "VariableExpImpl": 1,
      "PropertyCallExpImpl": 1
    },
    "properties": ["type"]
  },
  {
    "operations": {},
    "body": "aGlobalVariable.symbolName",
    "type": "TemplateExpression",
    "constructs": {
      "VariableExpImpl": 1,
      "PropertyCallExpImpl": 1
    },
    "properties": ["symbolName"]
  },
  {
    "operations": {},
    "body": "aGlobalVariable.initAtDefinition",
    "type": "IfExpression",
    "constructs": {
      "VariableExpImpl": 1,
      "PropertyCallExpImpl": 1
    },
    "properties": ["initAtDefinition"]
  },
  {
    "operations": {},
    "body": "aRteSource.rteLifecycleApiGroup",
    "type": "ForIter",
    "constructs": {
      "VariableExpImpl": 1,
      "PropertyCallExpImpl": 1
    },
    "properties": ["rteLifecycleApiGroup"]
  },
  {
    "operations": {},
    "body": "aGroup.memoryMapping",
    "type": "TemplateInvocationArgument",
    "constructs": {
      "VariableExpImpl": 1,
      "PropertyCallExpImpl": 1
    },
    "properties": ["memoryMapping"]
  },
  {
    "operations": {},
    "body": "aGroup.rteLifecycleApi",
    "type": "ForIter",
    "constructs": {
      "VariableExpImpl": 1,
      "PropertyCallExpImpl": 1
    },
    "properties": ["rteLifecycleApi"]
  },
  {
    "operations": {},
    "body": "aRteLifecycleApi",
    "type": "TemplateInvocationArgument",
    "constructs": {"VariableExpImpl": 1},
    "properties": []
  },
  {
    "operations": {},
    "body": "aGroup.memoryMapping",
    "type": "TemplateInvocationArgument",
    "constructs": {
      "VariableExpImpl": 1,
      "PropertyCallExpImpl": 1
    },
    "properties": ["memoryMapping"]
  },
  {
    "operations": {},
    "body": "aRteLifecycleApi.returnType.symbolName",
    "type": "TemplateExpression",
    "constructs": {
      "VariableExpImpl": 1,
      "PropertyCallExpImpl": 2
    },
    "properties": [
      "symbolName",
      "returnType"
    ]
  },
  {
    "operations": {},
    "body": "aRteLifecycleApi.symbolName",
    "type": "TemplateExpression",
    "constructs": {
      "VariableExpImpl": 1,
      "PropertyCallExpImpl": 1
    },
    "properties": ["symbolName"]
  },
  {
    "operations": {},
    "body": "aRteLifecycleApi",
    "type": "TemplateInvocationArgument",
    "constructs": {"VariableExpImpl": 1},
    "properties": []
  },
  {
    "operations": {},
    "body": "aRteLifecycleApi.operation",
    "type": "ForIter",
    "constructs": {
      "VariableExpImpl": 1,
      "PropertyCallExpImpl": 1
    },
    "properties": ["operation"]
  },
  {
    "operations": {},
    "body": "aInitializeOperation",
    "type": "TemplateInvocationArgument",
    "constructs": {"VariableExpImpl": 1},
    "properties": []
  },
  {
    "operations": {},
    "body": "aRteLifecycleApi.returnType.symbolName",
    "type": "TemplateExpression",
    "constructs": {
      "VariableExpImpl": 1,
      "PropertyCallExpImpl": 2
    },
    "properties": [
      "symbolName",
      "returnType"
    ]
  },
  {
    "operations": {},
    "body": "aRteLifecycleApi.symbolName",
    "type": "TemplateExpression",
    "constructs": {
      "VariableExpImpl": 1,
      "PropertyCallExpImpl": 1
    },
    "properties": ["symbolName"]
  },
  {
    "operations": {},
    "body": "aRteLifecycleApi",
    "type": "TemplateInvocationArgument",
    "constructs": {"VariableExpImpl": 1},
    "properties": []
  },
  {
    "operations": {},
    "body": "aRteLifecycleApi.coreStartApiImpl",
    "type": "ForIter",
    "constructs": {
      "VariableExpImpl": 1,
      "PropertyCallExpImpl": 1
    },
    "properties": ["coreStartApiImpl"]
  },
  {
    "operations": {},
    "body": "aRteCoreStartApiImpl.parent.coreId",
    "type": "TemplateExpression",
    "constructs": {
      "VariableExpImpl": 1,
      "PropertyCallExpImpl": 2
    },
    "properties": [
      "parent",
      "coreId"
    ]
  },
  {
    "operations": {},
    "body": "aRteCoreStartApiImpl.symbolName",
    "type": "TemplateExpression",
    "constructs": {
      "VariableExpImpl": 1,
      "PropertyCallExpImpl": 1
    },
    "properties": ["symbolName"]
  },
  {
    "operations": {},
    "body": "aRteLifecycleApi.returnType.symbolName",
    "type": "TemplateExpression",
    "constructs": {
      "VariableExpImpl": 1,
      "PropertyCallExpImpl": 2
    },
    "properties": [
      "symbolName",
      "returnType"
    ]
  },
  {
    "operations": {},
    "body": "aRteLifecycleApi.symbolName",
    "type": "TemplateExpression",
    "constructs": {
      "VariableExpImpl": 1,
      "PropertyCallExpImpl": 1
    },
    "properties": ["symbolName"]
  },
  {
    "operations": {},
    "body": "aRteLifecycleApi",
    "type": "TemplateInvocationArgument",
    "constructs": {"VariableExpImpl": 1},
    "properties": []
  },
  {
    "operations": {},
    "body": "aRteLifecycleApi.operation",
    "type": "ForIter",
    "constructs": {
      "VariableExpImpl": 1,
      "PropertyCallExpImpl": 1
    },
    "properties": ["operation"]
  },
  {
    "operations": {},
    "body": "aInitializeOperation",
    "type": "TemplateInvocationArgument",
    "constructs": {"VariableExpImpl": 1},
    "properties": []
  },
  {
    "operations": {},
    "body": "aRteLifecycleApi.returnType.symbolName",
    "type": "TemplateExpression",
    "constructs": {
      "VariableExpImpl": 1,
      "PropertyCallExpImpl": 2
    },
    "properties": [
      "symbolName",
      "returnType"
    ]
  },
  {
    "operations": {},
    "body": "aRteLifecycleApi.symbolName",
    "type": "TemplateExpression",
    "constructs": {
      "VariableExpImpl": 1,
      "PropertyCallExpImpl": 1
    },
    "properties": ["symbolName"]
  },
  {
    "operations": {},
    "body": "aRteLifecycleApi",
    "type": "TemplateInvocationArgument",
    "constructs": {"VariableExpImpl": 1},
    "properties": []
  },
  {
    "operations": {},
    "body": "aRteLifecycleApi.returnType.symbolName",
    "type": "TemplateExpression",
    "constructs": {
      "VariableExpImpl": 1,
      "PropertyCallExpImpl": 2
    },
    "properties": [
      "symbolName",
      "returnType"
    ]
  },
  {
    "operations": {},
    "body": "aRteLifecycleApi.symbolName",
    "type": "TemplateExpression",
    "constructs": {
      "VariableExpImpl": 1,
      "PropertyCallExpImpl": 1
    },
    "properties": ["symbolName"]
  },
  {
    "operations": {},
    "body": "aRteLifecycleApi",
    "type": "TemplateInvocationArgument",
    "constructs": {"VariableExpImpl": 1},
    "properties": []
  },
  {
    "operations": {},
    "body": "aRteLifecycleApi.operation",
    "type": "ForIter",
    "constructs": {
      "VariableExpImpl": 1,
      "PropertyCallExpImpl": 1
    },
    "properties": ["operation"]
  },
  {
    "operations": {},
    "body": "aInitializeOperation",
    "type": "TemplateInvocationArgument",
    "constructs": {"VariableExpImpl": 1},
    "properties": []
  },
  {
    "operations": {},
    "body": "aRteLifecycleApi.returnType.symbolName",
    "type": "TemplateExpression",
    "constructs": {
      "VariableExpImpl": 1,
      "PropertyCallExpImpl": 2
    },
    "properties": [
      "symbolName",
      "returnType"
    ]
  },
  {
    "operations": {},
    "body": "aRteLifecycleApi.symbolName",
    "type": "TemplateExpression",
    "constructs": {
      "VariableExpImpl": 1,
      "PropertyCallExpImpl": 1
    },
    "properties": ["symbolName"]
  },
  {
    "operations": {},
    "body": "aRteLifecycleApi",
    "type": "TemplateInvocationArgument",
    "constructs": {"VariableExpImpl": 1},
    "properties": []
  },
  {
    "operations": {},
    "body": "aInterPartitionTimeoutOperation",
    "type": "TemplateInvocationArgument",
    "constructs": {"VariableExpImpl": 1},
    "properties": []
  },
  {
    "operations": {},
    "body": "aRteLifecycleApi.returnType.symbolName",
    "type": "TemplateExpression",
    "constructs": {
      "VariableExpImpl": 1,
      "PropertyCallExpImpl": 2
    },
    "properties": [
      "symbolName",
      "returnType"
    ]
  },
  {
    "operations": {},
    "body": "aRteLifecycleApi.symbolName",
    "type": "TemplateExpression",
    "constructs": {
      "VariableExpImpl": 1,
      "PropertyCallExpImpl": 1
    },
    "properties": ["symbolName"]
  },
  {
    "operations": {},
    "body": "aRteLifecycleApi",
    "type": "TemplateInvocationArgument",
    "constructs": {"VariableExpImpl": 1},
    "properties": []
  },
  {
    "operations": {},
    "body": "aInterPartitionTimeoutOperation",
    "type": "TemplateInvocationArgument",
    "constructs": {"VariableExpImpl": 1},
    "properties": []
  },
  {
    "operations": {},
    "body": "aRteSource.schmLifecycleApiGroup",
    "type": "ForIter",
    "constructs": {
      "VariableExpImpl": 1,
      "PropertyCallExpImpl": 1
    },
    "properties": ["schmLifecycleApiGroup"]
  },
  {
    "operations": {},
    "body": "aGroup.memoryMapping",
    "type": "TemplateInvocationArgument",
    "constructs": {
      "VariableExpImpl": 1,
      "PropertyCallExpImpl": 1
    },
    "properties": ["memoryMapping"]
  },
  {
    "operations": {},
    "body": "aGroup.schmLifecycleApi",
    "type": "ForIter",
    "constructs": {
      "VariableExpImpl": 1,
      "PropertyCallExpImpl": 1
    },
    "properties": ["schmLifecycleApi"]
  },
  {
    "operations": {},
    "body": "aSchmLifecycleApi",
    "type": "TemplateInvocationArgument",
    "constructs": {"VariableExpImpl": 1},
    "properties": []
  },
  {
    "operations": {},
    "body": "aGroup.memoryMapping",
    "type": "TemplateInvocationArgument",
    "constructs": {
      "VariableExpImpl": 1,
      "PropertyCallExpImpl": 1
    },
    "properties": ["memoryMapping"]
  },
  {
    "operations": {},
    "body": "aSchmLifecycleApi",
    "type": "TemplateInvocationArgument",
    "constructs": {"VariableExpImpl": 1},
    "properties": []
  },
  {
    "operations": {},
    "body": "aSchmLifecycleApi.returnType.symbolName",
    "type": "TemplateExpression",
    "constructs": {
      "VariableExpImpl": 1,
      "PropertyCallExpImpl": 2
    },
    "properties": [
      "symbolName",
      "returnType"
    ]
  },
  {
    "operations": {},
    "body": "aSchmLifecycleApi.symbolName",
    "type": "TemplateExpression",
    "constructs": {
      "VariableExpImpl": 1,
      "PropertyCallExpImpl": 1
    },
    "properties": ["symbolName"]
  },
  {
    "operations": {},
    "body": "aSchmLifecycleApi",
    "type": "TemplateInvocationArgument",
    "constructs": {"VariableExpImpl": 1},
    "properties": []
  },
  {
    "operations": {},
    "body": "aSchmLifecycleApi.coreInitApiImpl",
    "type": "ForIter",
    "constructs": {
      "VariableExpImpl": 1,
      "PropertyCallExpImpl": 1
    },
    "properties": ["coreInitApiImpl"]
  },
  {
    "operations": {},
    "body": "aSchmCoreInitApiImpl.parent.coreId",
    "type": "TemplateExpression",
    "constructs": {
      "VariableExpImpl": 1,
      "PropertyCallExpImpl": 2
    },
    "properties": [
      "parent",
      "coreId"
    ]
  },
  {
    "operations": {},
    "body": "aSchmCoreInitApiImpl.symbolName",
    "type": "TemplateExpression",
    "constructs": {
      "VariableExpImpl": 1,
      "PropertyCallExpImpl": 1
    },
    "properties": ["symbolName"]
  },
  {
    "operations": {},
    "body": "aSchmLifecycleApi",
    "type": "TemplateInvocationArgument",
    "constructs": {"VariableExpImpl": 1},
    "properties": []
  },
  {
    "operations": {},
    "body": "aSchmLifecycleApi.returnType.symbolName",
    "type": "TemplateExpression",
    "constructs": {
      "VariableExpImpl": 1,
      "PropertyCallExpImpl": 2
    },
    "properties": [
      "symbolName",
      "returnType"
    ]
  },
  {
    "operations": {},
    "body": "aSchmLifecycleApi.symbolName",
    "type": "TemplateExpression",
    "constructs": {
      "VariableExpImpl": 1,
      "PropertyCallExpImpl": 1
    },
    "properties": ["symbolName"]
  },
  {
    "operations": {},
    "body": "aSchmLifecycleApi",
    "type": "TemplateInvocationArgument",
    "constructs": {"VariableExpImpl": 1},
    "properties": []
  },
  {
    "operations": {},
    "body": "aSchmLifecycleApi.operation",
    "type": "ForIter",
    "constructs": {
      "VariableExpImpl": 1,
      "PropertyCallExpImpl": 1
    },
    "properties": ["operation"]
  },
  {
    "operations": {},
    "body": "aInitializeOperation",
    "type": "TemplateInvocationArgument",
    "constructs": {"VariableExpImpl": 1},
    "properties": []
  },
  {
    "operations": {},
    "body": "aSchmLifecycleApi.initTargetModeMachineInstance",
    "type": "ForIter",
    "constructs": {
      "VariableExpImpl": 1,
      "PropertyCallExpImpl": 1
    },
    "properties": ["initTargetModeMachineInstance"]
  },
  {
    "operations": {},
    "body": "aModeMachineInstance.currentModeVariable.symbolName",
    "type": "TemplateExpression",
    "constructs": {
      "VariableExpImpl": 1,
      "PropertyCallExpImpl": 2
    },
    "properties": [
      "currentModeVariable",
      "symbolName"
    ]
  },
  {
    "operations": {},
    "body": "aModeMachineInstance.initModeConstant.symbolName",
    "type": "TemplateExpression",
    "constructs": {
      "VariableExpImpl": 1,
      "PropertyCallExpImpl": 2
    },
    "properties": [
      "initModeConstant",
      "symbolName"
    ]
  },
  {
    "operations": {},
    "body": "aModeMachineInstance.nextModeVariable.symbolName",
    "type": "TemplateExpression",
    "constructs": {
      "VariableExpImpl": 1,
      "PropertyCallExpImpl": 2
    },
    "properties": [
      "nextModeVariable",
      "symbolName"
    ]
  },
  {
    "operations": {},
    "body": "aModeMachineInstance.initModeConstant.symbolName",
    "type": "TemplateExpression",
    "constructs": {
      "VariableExpImpl": 1,
      "PropertyCallExpImpl": 2
    },
    "properties": [
      "initModeConstant",
      "symbolName"
    ]
  },
  {
    "operations": {},
    "body": "aModeMachineInstance.requestModeQueue.symbolName",
    "type": "TemplateExpression",
    "constructs": {
      "VariableExpImpl": 1,
      "PropertyCallExpImpl": 2
    },
    "properties": [
      "requestModeQueue",
      "symbolName"
    ]
  },
  {
    "operations": {},
    "body": "aSchmLifecycleApi.initialExecutableStartOperation",
    "type": "ForIter",
    "constructs": {
      "VariableExpImpl": 1,
      "PropertyCallExpImpl": 1
    },
    "properties": ["initialExecutableStartOperation"]
  },
  {
    "operations": {},
    "body": "aExecutableStartOperation",
    "type": "TemplateInvocationArgument",
    "constructs": {"VariableExpImpl": 1},
    "properties": []
  },
  {
    "operations": {},
    "body": "aSchmLifecycleApi.initialExecutableOsTaskEvent",
    "type": "ForIter",
    "constructs": {
      "VariableExpImpl": 1,
      "PropertyCallExpImpl": 1
    },
    "properties": ["initialExecutableOsTaskEvent"]
  },
  {
    "operations": {"isEmpty": 1},
    "body": "aOsTaskEvent.osEventId->isEmpty()",
    "type": "IfExpression",
    "constructs": {
      "OperationCallExpImpl": 1,
      "VariableExpImpl": 1,
      "PropertyCallExpImpl": 1
    },
    "properties": ["osEventId"]
  },
  {
    "operations": {},
    "body": "aOsTaskEvent.osTaskId",
    "type": "TemplateExpression",
    "constructs": {
      "VariableExpImpl": 1,
      "PropertyCallExpImpl": 1
    },
    "properties": ["osTaskId"]
  },
  {
    "operations": {"sep": 1},
    "body": "aOsTaskEvent.osEventId->sep('|')",
    "type": "TemplateExpression",
    "constructs": {
      "VariableExpImpl": 1,
      "OperationCallExpImpl": 1,
      "StringLiteralExpImpl": 1,
      "PropertyCallExpImpl": 1
    },
    "properties": ["osEventId"]
  },
  {
    "operations": {},
    "body": "aOsTaskEvent.osTaskId",
    "type": "TemplateExpression",
    "constructs": {
      "VariableExpImpl": 1,
      "PropertyCallExpImpl": 1
    },
    "properties": ["osTaskId"]
  },
  {
    "operations": {},
    "body": "aSchmLifecycleApi.returnType.symbolName",
    "type": "TemplateExpression",
    "constructs": {
      "VariableExpImpl": 1,
      "PropertyCallExpImpl": 2
    },
    "properties": [
      "symbolName",
      "returnType"
    ]
  },
  {
    "operations": {},
    "body": "aSchmLifecycleApi.symbolName",
    "type": "TemplateExpression",
    "constructs": {
      "VariableExpImpl": 1,
      "PropertyCallExpImpl": 1
    },
    "properties": ["symbolName"]
  },
  {
    "operations": {},
    "body": "aSchmLifecycleApi",
    "type": "TemplateInvocationArgument",
    "constructs": {"VariableExpImpl": 1},
    "properties": []
  },
  {
    "operations": {},
    "body": "aRteSource.taskBodyGroup",
    "type": "ForIter",
    "constructs": {
      "VariableExpImpl": 1,
      "PropertyCallExpImpl": 1
    },
    "properties": ["taskBodyGroup"]
  },
  {
    "operations": {},
    "body": "aGroup.memoryMapping",
    "type": "TemplateInvocationArgument",
    "constructs": {
      "VariableExpImpl": 1,
      "PropertyCallExpImpl": 1
    },
    "properties": ["memoryMapping"]
  },
  {
    "operations": {},
    "body": "aGroup.taskBody",
    "type": "ForIter",
    "constructs": {
      "VariableExpImpl": 1,
      "PropertyCallExpImpl": 1
    },
    "properties": ["taskBody"]
  },
  {
    "operations": {},
    "body": "aTaskBody",
    "type": "TemplateInvocationArgument",
    "constructs": {"VariableExpImpl": 1},
    "properties": []
  },
  {
    "operations": {},
    "body": "aGroup.memoryMapping",
    "type": "TemplateInvocationArgument",
    "constructs": {
      "VariableExpImpl": 1,
      "PropertyCallExpImpl": 1
    },
    "properties": ["memoryMapping"]
  },
  {
    "operations": {},
    "body": "aTaskBody.symbolName",
    "type": "TemplateExpression",
    "constructs": {
      "VariableExpImpl": 1,
      "PropertyCallExpImpl": 1
    },
    "properties": ["symbolName"]
  },
  {
    "operations": {},
    "body": "aTaskBody.operation",
    "type": "TemplateInvocationArgument",
    "constructs": {
      "VariableExpImpl": 1,
      "PropertyCallExpImpl": 1
    },
    "properties": ["operation"]
  },
  {
    "operations": {},
    "body": "aTaskBody.symbolName",
    "type": "TemplateExpression",
    "constructs": {
      "VariableExpImpl": 1,
      "PropertyCallExpImpl": 1
    },
    "properties": ["symbolName"]
  },
  {
    "operations": {},
    "body": "aTaskBody",
    "type": "TemplateInvocationArgument",
    "constructs": {"VariableExpImpl": 1},
    "properties": []
  },
  {
    "operations": {},
    "body": "aTaskBody",
    "type": "TemplateInvocationArgument",
    "constructs": {"VariableExpImpl": 1},
    "properties": []
  },
  {
    "operations": {},
    "body": "aTaskBody.operation",
    "type": "TemplateInvocationArgument",
    "constructs": {
      "VariableExpImpl": 1,
      "PropertyCallExpImpl": 1
    },
    "properties": ["operation"]
  },
  {
    "operations": {},
    "body": "aTaskBody.symbolName",
    "type": "TemplateExpression",
    "constructs": {
      "VariableExpImpl": 1,
      "PropertyCallExpImpl": 1
    },
    "properties": ["symbolName"]
  },
  {
    "operations": {},
    "body": "aTaskBody",
    "type": "TemplateInvocationArgument",
    "constructs": {"VariableExpImpl": 1},
    "properties": []
  },
  {
    "operations": {},
    "body": "aTaskBody",
    "type": "TemplateInvocationArgument",
    "constructs": {"VariableExpImpl": 1},
    "properties": []
  },
  {
    "operations": {"sep": 1},
    "body": "aTaskBody.osEventId->sep(' | ')",
    "type": "TemplateExpression",
    "constructs": {
      "VariableExpImpl": 1,
      "OperationCallExpImpl": 1,
      "StringLiteralExpImpl": 1,
      "PropertyCallExpImpl": 1
    },
    "properties": ["osEventId"]
  },
  {
    "operations": {},
    "body": "aTaskBody.checksOsEventId",
    "type": "IfExpression",
    "constructs": {
      "VariableExpImpl": 1,
      "PropertyCallExpImpl": 1
    },
    "properties": ["checksOsEventId"]
  },
  {
    "operations": {"sep": 1},
    "body": "aTaskBody.osEventId->sep(' | ')",
    "type": "TemplateExpression",
    "constructs": {
      "OperationCallExpImpl": 1,
      "VariableExpImpl": 1,
      "StringLiteralExpImpl": 1,
      "PropertyCallExpImpl": 1
    },
    "properties": ["osEventId"]
  },
  {
    "operations": {},
    "body": "aTaskBody.osTaskId",
    "type": "TemplateExpression",
    "constructs": {
      "VariableExpImpl": 1,
      "PropertyCallExpImpl": 1
    },
    "properties": ["osTaskId"]
  },
  {
    "operations": {},
    "body": "aTaskBody.eventVariable",
    "type": "TemplateInvocationArgument",
    "constructs": {
      "VariableExpImpl": 1,
      "PropertyCallExpImpl": 1
    },
    "properties": ["eventVariable"]
  },
  {
    "operations": {},
    "body": "aTaskBody.eventVariable",
    "type": "TemplateInvocationArgument",
    "constructs": {
      "VariableExpImpl": 1,
      "PropertyCallExpImpl": 1
    },
    "properties": ["eventVariable"]
  },
  {
    "operations": {},
    "body": "aTaskBody.operation",
    "type": "ForIter",
    "constructs": {
      "VariableExpImpl": 1,
      "PropertyCallExpImpl": 1
    },
    "properties": ["operation"]
  },
  {
    "operations": {},
    "body": "aTaskBody.checksOsEventId",
    "type": "IfExpression",
    "constructs": {
      "VariableExpImpl": 1,
      "PropertyCallExpImpl": 1
    },
    "properties": ["checksOsEventId"]
  },
  {
    "operations": {},
    "body": "aOsEventSetActivationOperation",
    "type": "TemplateInvocationArgument",
    "constructs": {"VariableExpImpl": 1},
    "properties": []
  },
  {
    "operations": {},
    "body": "aTaskBody.eventVariable",
    "type": "TemplateInvocationArgument",
    "constructs": {
      "VariableExpImpl": 1,
      "PropertyCallExpImpl": 1
    },
    "properties": ["eventVariable"]
  },
  {
    "operations": {},
    "body": "aOsEventSetActivationOperation.activationOsEventId",
    "type": "TemplateExpression",
    "constructs": {
      "VariableExpImpl": 1,
      "PropertyCallExpImpl": 1
    },
    "properties": ["activationOsEventId"]
  },
  {
    "operations": {},
    "body": "aOsEventSetActivationOperation",
    "type": "TemplateInvocationArgument",
    "constructs": {"VariableExpImpl": 1},
    "properties": []
  },
  {
    "operations": {},
    "body": "aTaskBody.symbolName",
    "type": "TemplateExpression",
    "constructs": {
      "VariableExpImpl": 1,
      "PropertyCallExpImpl": 1
    },
    "properties": ["symbolName"]
  },
  {
    "operations": {},
    "body": "aTaskBody.osEventId",
    "type": "TemplateExpression",
    "constructs": {
      "VariableExpImpl": 1,
      "PropertyCallExpImpl": 1
    },
    "properties": ["osEventId"]
  },
  {
    "operations": {},
    "body": "aTaskBody.osEventId",
    "type": "TemplateExpression",
    "constructs": {
      "VariableExpImpl": 1,
      "PropertyCallExpImpl": 1
    },
    "properties": ["osEventId"]
  },
  {
    "operations": {},
    "body": "aTaskBody.startEntity.symbolName",
    "type": "TemplateExpression",
    "constructs": {
      "VariableExpImpl": 1,
      "PropertyCallExpImpl": 2
    },
    "properties": [
      "symbolName",
      "startEntity"
    ]
  },
  {
    "operations": {},
    "body": "aRteSource.trustedFunctionGroup",
    "type": "ForIter",
    "constructs": {
      "VariableExpImpl": 1,
      "PropertyCallExpImpl": 1
    },
    "properties": ["trustedFunctionGroup"]
  },
  {
    "operations": {},
    "body": "aGroup.memoryMapping",
    "type": "TemplateInvocationArgument",
    "constructs": {
      "VariableExpImpl": 1,
      "PropertyCallExpImpl": 1
    },
    "properties": ["memoryMapping"]
  },
  {
    "operations": {},
    "body": "aGroup.trustedFunction",
    "type": "ForIter",
    "constructs": {
      "VariableExpImpl": 1,
      "PropertyCallExpImpl": 1
    },
    "properties": ["trustedFunction"]
  },
  {
    "operations": {},
    "body": "aTrustedFunction",
    "type": "TemplateInvocationArgument",
    "constructs": {"VariableExpImpl": 1},
    "properties": []
  },
  {
    "operations": {},
    "body": "aGroup.memoryMapping",
    "type": "TemplateInvocationArgument",
    "constructs": {
      "VariableExpImpl": 1,
      "PropertyCallExpImpl": 1
    },
    "properties": ["memoryMapping"]
  },
  {
    "operations": {},
    "body": "aTrustedFunction.returnType.symbolName",
    "type": "TemplateExpression",
    "constructs": {
      "VariableExpImpl": 1,
      "PropertyCallExpImpl": 2
    },
    "properties": [
      "symbolName",
      "returnType"
    ]
  },
  {
    "operations": {},
    "body": "aTrustedFunction.symbolName",
    "type": "TemplateExpression",
    "constructs": {
      "VariableExpImpl": 1,
      "PropertyCallExpImpl": 1
    },
    "properties": ["symbolName"]
  },
  {
    "operations": {},
    "body": "aTrustedFunction",
    "type": "TemplateInvocationArgument",
    "constructs": {"VariableExpImpl": 1},
    "properties": []
  },
  {
    "operations": {},
    "body": "aTrustedFunction.localVariable->collect(temp1 : LocalVariable | temp1.type)->collect(temp2 : Type | temp2.symbolName)",
    "type": "TemplateExpression",
    "constructs": {
      "IteratorExpImpl": 2,
      "VariableExpImpl": 3,
      "PropertyCallExpImpl": 3
    },
    "properties": [
      "symbolName",
      "type",
      "localVariable"
    ]
  },
  {
    "operations": {},
    "body": "aTrustedFunction.localVariable->collect(temp1 : LocalVariable | temp1.type)->collect(temp2 : Type | temp2.symbolName)",
    "type": "TemplateExpression",
    "constructs": {
      "IteratorExpImpl": 2,
      "VariableExpImpl": 3,
      "PropertyCallExpImpl": 3
    },
    "properties": [
      "symbolName",
      "type",
      "localVariable"
    ]
  },
  {
    "operations": {},
    "body": "aTrustedFunction.signalGroupSymbolName",
    "type": "TemplateExpression",
    "constructs": {
      "VariableExpImpl": 1,
      "PropertyCallExpImpl": 1
    },
    "properties": ["signalGroupSymbolName"]
  },
  {
    "operations": {},
    "body": "aTrustedFunction.isGroup",
    "type": "IfExpression",
    "constructs": {
      "VariableExpImpl": 1,
      "PropertyCallExpImpl": 1
    },
    "properties": ["isGroup"]
  },
  {
    "operations": {},
    "body": "aTrustedFunction.returnType.symbolName",
    "type": "TemplateExpression",
    "constructs": {
      "VariableExpImpl": 1,
      "PropertyCallExpImpl": 2
    },
    "properties": [
      "symbolName",
      "returnType"
    ]
  },
  {
    "operations": {},
    "body": "aTrustedFunction.symbolName",
    "type": "TemplateExpression",
    "constructs": {
      "VariableExpImpl": 1,
      "PropertyCallExpImpl": 1
    },
    "properties": ["symbolName"]
  },
  {
    "operations": {},
    "body": "aTrustedFunction",
    "type": "TemplateInvocationArgument",
    "constructs": {"VariableExpImpl": 1},
    "properties": []
  },
  {
    "operations": {
      "or": 1,
      "oclIsKindOf": 2
    },
    "body": "aTrustedFunction.operation.accessVariable.valueVariable.type.oclIsKindOf(rte::module::PrimitiveType).or(aTrustedFunction.operation.accessVariable.valueVariable.type.oclIsKindOf(rte::module::PointerType))",
    "type": "IfExpression",
    "constructs": {
      "VariableExpImpl": 2,
      "OperationCallExpImpl": 3,
      "TypeExpImpl": 2,
      "PropertyCallExpImpl": 8
    },
    "properties": [
      "operation",
      "accessVariable",
      "valueVariable",
      "type"
    ]
  },
  {
    "operations": {},
    "body": "aExcludeOperation",
    "type": "TemplateInvocationArgument",
    "constructs": {"VariableExpImpl": 1},
    "properties": []
  },
  {
    "operations": {"oclIsKindOf": 1},
    "body": "aTrustedFunction.operation.accessVariable.valueVariable.type.oclIsKindOf(rte::module::ArrayType)",
    "type": "IfExpression",
    "constructs": {
      "OperationCallExpImpl": 1,
      "VariableExpImpl": 1,
      "TypeExpImpl": 1,
      "PropertyCallExpImpl": 4
    },
    "properties": [
      "operation",
      "accessVariable",
      "valueVariable",
      "type"
    ]
  },
  {
    "operations": {"oclIsKindOf": 1},
    "body": "aTrustedFunction.operation.accessVariable.valueVariable.type.oclIsKindOf(rte::module::StructType)",
    "type": "IfExpression",
    "constructs": {
      "VariableExpImpl": 1,
      "OperationCallExpImpl": 1,
      "TypeExpImpl": 1,
      "PropertyCallExpImpl": 4
    },
    "properties": [
      "operation",
      "accessVariable",
      "valueVariable",
      "type"
    ]
  },
  {
    "operations": {},
    "body": "aTrustedFunction.operation.accessVariable.valueVariable.symbolName",
    "type": "TemplateExpression",
    "constructs": {
      "VariableExpImpl": 1,
      "PropertyCallExpImpl": 4
    },
    "properties": [
      "operation",
      "accessVariable",
      "valueVariable",
      "symbolName"
    ]
  },
  {
    "operations": {},
    "body": "aTrustedFunction.operation.accessVariable.valueVariable.type.symbolName",
    "type": "TemplateExpression",
    "constructs": {
      "VariableExpImpl": 1,
      "PropertyCallExpImpl": 5
    },
    "properties": [
      "operation",
      "accessVariable",
      "symbolName",
      "valueVariable",
      "type"
    ]
  },
  {
    "operations": {"oclIsKindOf": 1},
    "body": "aTrustedFunction.operation.accessVariable.valueVariable.type.oclIsKindOf(rte::module::UnionType)",
    "type": "IfExpression",
    "constructs": {
      "OperationCallExpImpl": 1,
      "VariableExpImpl": 1,
      "TypeExpImpl": 1,
      "PropertyCallExpImpl": 4
    },
    "properties": [
      "operation",
      "accessVariable",
      "valueVariable",
      "type"
    ]
  },
  {
    "operations": {},
    "body": "aTrustedFunction.operation.accessVariable.valueVariable.symbolName",
    "type": "TemplateExpression",
    "constructs": {
      "VariableExpImpl": 1,
      "PropertyCallExpImpl": 4
    },
    "properties": [
      "operation",
      "accessVariable",
      "valueVariable",
      "symbolName"
    ]
  },
  {
    "operations": {},
    "body": "aTrustedFunction.operation.accessVariable.valueVariable.type.symbolName",
    "type": "TemplateExpression",
    "constructs": {
      "VariableExpImpl": 1,
      "PropertyCallExpImpl": 5
    },
    "properties": [
      "operation",
      "accessVariable",
      "symbolName",
      "valueVariable",
      "type"
    ]
  },
  {
    "operations": {},
    "body": "aTrustedFunction.operation.accessVariable.valueVariable.symbolName",
    "type": "TemplateExpression",
    "constructs": {
      "VariableExpImpl": 1,
      "PropertyCallExpImpl": 4
    },
    "properties": [
      "operation",
      "accessVariable",
      "valueVariable",
      "symbolName"
    ]
  },
  {
    "operations": {},
    "body": "aTrustedFunction.operation.accessVariable.valueVariable.type.originalTypeSymbolName",
    "type": "TemplateExpression",
    "constructs": {
      "VariableExpImpl": 1,
      "PropertyCallExpImpl": 5
    },
    "properties": [
      "operation",
      "accessVariable",
      "valueVariable",
      "type",
      "originalTypeSymbolName"
    ]
  },
  {
    "operations": {},
    "body": "aTrustedFunction.operation.accessVariable.valueVariable.type.symbolName",
    "type": "TemplateExpression",
    "constructs": {
      "VariableExpImpl": 1,
      "PropertyCallExpImpl": 5
    },
    "properties": [
      "operation",
      "accessVariable",
      "symbolName",
      "valueVariable",
      "type"
    ]
  },
  {
    "operations": {
      "not": 1,
      "oclIsUndefined": 1
    },
    "body": "aTrustedFunction.operation.accessVariable.statusVariable.oclIsUndefined().not()",
    "type": "IfExpression",
    "constructs": {
      "VariableExpImpl": 1,
      "OperationCallExpImpl": 2,
      "PropertyCallExpImpl": 3
    },
    "properties": [
      "operation",
      "statusVariable",
      "accessVariable"
    ]
  },
  {
    "operations": {},
    "body": "aTrustedFunction.operation.accessVariable.statusVariable.symbolName",
    "type": "TemplateExpression",
    "constructs": {
      "VariableExpImpl": 1,
      "PropertyCallExpImpl": 4
    },
    "properties": [
      "operation",
      "statusVariable",
      "accessVariable",
      "symbolName"
    ]
  },
  {
    "operations": {},
    "body": "aTrustedFunction.operation.sendStatus",
    "type": "TemplateInvocationArgument",
    "constructs": {
      "VariableExpImpl": 1,
      "PropertyCallExpImpl": 2
    },
    "properties": [
      "operation",
      "sendStatus"
    ]
  },
  {
    "operations": {},
    "body": "aExcludeOperation",
    "type": "TemplateInvocationArgument",
    "constructs": {"VariableExpImpl": 1},
    "properties": []
  },
  {
    "operations": {},
    "body": "aTrustedFunction",
    "type": "TemplateInvocationArgument",
    "constructs": {"VariableExpImpl": 1},
    "properties": []
  },
  {
    "operations": {},
    "body": "aTrustedFunction",
    "type": "TemplateInvocationArgument",
    "constructs": {"VariableExpImpl": 1},
    "properties": []
  },
  {
    "operations": {},
    "body": "aTrustedFunction.dataVariable",
    "type": "TemplateInvocationArgument",
    "constructs": {
      "VariableExpImpl": 1,
      "PropertyCallExpImpl": 1
    },
    "properties": ["dataVariable"]
  },
  {
    "operations": {},
    "body": "aTrustedFunction.dataVariable.type.symbolName",
    "type": "TemplateExpression",
    "constructs": {
      "VariableExpImpl": 1,
      "PropertyCallExpImpl": 3
    },
    "properties": [
      "dataVariable",
      "symbolName",
      "type"
    ]
  },
  {
    "operations": {},
    "body": "aTrustedFunction.operation",
    "type": "TemplateInvocationArgument",
    "constructs": {
      "VariableExpImpl": 1,
      "PropertyCallExpImpl": 1
    },
    "properties": ["operation"]
  },
  {
    "operations": {
      "not": 1,
      "oclIsUndefined": 1
    },
    "body": "aTrustedFunction.operation.filterOperation.oclIsUndefined().not()",
    "type": "IfExpression",
    "constructs": {
      "OperationCallExpImpl": 2,
      "VariableExpImpl": 1,
      "PropertyCallExpImpl": 2
    },
    "properties": [
      "operation",
      "filterOperation"
    ]
  },
  {
    "operations": {},
    "body": "aTrustedFunction.operation.filterOperation.filterResultVariable",
    "type": "TemplateInvocationArgument",
    "constructs": {
      "VariableExpImpl": 1,
      "PropertyCallExpImpl": 3
    },
    "properties": [
      "operation",
      "filterResultVariable",
      "filterOperation"
    ]
  },
  {
    "operations": {},
    "body": "aTrustedFunction.returnType.symbolName",
    "type": "TemplateExpression",
    "constructs": {
      "VariableExpImpl": 1,
      "PropertyCallExpImpl": 2
    },
    "properties": [
      "symbolName",
      "returnType"
    ]
  },
  {
    "operations": {},
    "body": "aTrustedFunction.symbolName",
    "type": "TemplateExpression",
    "constructs": {
      "VariableExpImpl": 1,
      "PropertyCallExpImpl": 1
    },
    "properties": ["symbolName"]
  },
  {
    "operations": {},
    "body": "aTrustedFunction",
    "type": "TemplateInvocationArgument",
    "constructs": {"VariableExpImpl": 1},
    "properties": []
  },
  {
    "operations": {},
    "body": "aTrustedFunction",
    "type": "TemplateInvocationArgument",
    "constructs": {"VariableExpImpl": 1},
    "properties": []
  },
  {
    "operations": {},
    "body": "aTrustedFunction",
    "type": "TemplateInvocationArgument",
    "constructs": {"VariableExpImpl": 1},
    "properties": []
  },
  {
    "operations": {},
    "body": "aTrustedFunction.operation",
    "type": "TemplateInvocationArgument",
    "constructs": {
      "VariableExpImpl": 1,
      "PropertyCallExpImpl": 1
    },
    "properties": ["operation"]
  },
  {
    "operations": {
      "not": 1,
      "oclIsUndefined": 1
    },
    "body": "aTrustedFunction.operation.filterOperation.oclIsUndefined().not()",
    "type": "IfExpression",
    "constructs": {
      "OperationCallExpImpl": 2,
      "VariableExpImpl": 1,
      "PropertyCallExpImpl": 2
    },
    "properties": [
      "filterOperation",
      "operation"
    ]
  },
  {
    "operations": {},
    "body": "aTrustedFunction.operation.filterOperation.filterResultVariable",
    "type": "TemplateInvocationArgument",
    "constructs": {
      "VariableExpImpl": 1,
      "PropertyCallExpImpl": 3
    },
    "properties": [
      "filterResultVariable",
      "filterOperation",
      "operation"
    ]
  },
  {
    "operations": {},
    "body": "aTrustedFunction.returnType.symbolName",
    "type": "TemplateExpression",
    "constructs": {
      "VariableExpImpl": 1,
      "PropertyCallExpImpl": 2
    },
    "properties": [
      "symbolName",
      "returnType"
    ]
  },
  {
    "operations": {},
    "body": "aTrustedFunction.symbolName",
    "type": "TemplateExpression",
    "constructs": {
      "VariableExpImpl": 1,
      "PropertyCallExpImpl": 1
    },
    "properties": ["symbolName"]
  },
  {
    "operations": {},
    "body": "aTrustedFunction",
    "type": "TemplateInvocationArgument",
    "constructs": {"VariableExpImpl": 1},
    "properties": []
  },
  {
    "operations": {},
    "body": "aExcludeOperation",
    "type": "TemplateInvocationArgument",
    "constructs": {"VariableExpImpl": 1},
    "properties": []
  },
  {
    "operations": {"oclIsKindOf": 1},
    "body": "aTrustedFunction.operation.type.oclIsKindOf(rte::module::ArrayType)",
    "type": "IfExpression",
    "constructs": {
      "OperationCallExpImpl": 1,
      "VariableExpImpl": 1,
      "TypeExpImpl": 1,
      "PropertyCallExpImpl": 2
    },
    "properties": [
      "operation",
      "type"
    ]
  },
  {
    "operations": {},
    "body": "aTrustedFunction.operation.accessVariable",
    "type": "TemplateInvocationArgument",
    "constructs": {
      "VariableExpImpl": 1,
      "PropertyCallExpImpl": 2
    },
    "properties": [
      "operation",
      "accessVariable"
    ]
  },
  {
    "operations": {},
    "body": "aTrustedFunction.operation.type.symbolName",
    "type": "TemplateExpression",
    "constructs": {
      "VariableExpImpl": 1,
      "PropertyCallExpImpl": 3
    },
    "properties": [
      "operation",
      "symbolName",
      "type"
    ]
  },
  {
    "operations": {},
    "body": "aTrustedFunction.operation.accessVariable.queueType.maxLengthConstant",
    "type": "TemplateInvocationArgument",
    "constructs": {
      "VariableExpImpl": 1,
      "PropertyCallExpImpl": 4
    },
    "properties": [
      "maxLengthConstant",
      "operation",
      "queueType",
      "accessVariable"
    ]
  },
  {
    "operations": {"oclIsKindOf": 1},
    "body": "aTrustedFunction.operation.type.oclIsKindOf(rte::module::StructType)",
    "type": "IfExpression",
    "constructs": {
      "OperationCallExpImpl": 1,
      "VariableExpImpl": 1,
      "TypeExpImpl": 1,
      "PropertyCallExpImpl": 2
    },
    "properties": [
      "operation",
      "type"
    ]
  },
  {
    "operations": {},
    "body": "aTrustedFunction.operation.accessVariable",
    "type": "TemplateInvocationArgument",
    "constructs": {
      "VariableExpImpl": 1,
      "PropertyCallExpImpl": 2
    },
    "properties": [
      "operation",
      "accessVariable"
    ]
  },
  {
    "operations": {},
    "body": "aTrustedFunction.operation.type.symbolName",
    "type": "TemplateExpression",
    "constructs": {
      "VariableExpImpl": 1,
      "PropertyCallExpImpl": 3
    },
    "properties": [
      "operation",
      "symbolName",
      "type"
    ]
  },
  {
    "operations": {},
    "body": "aTrustedFunction.operation.type.symbolName",
    "type": "TemplateExpression",
    "constructs": {
      "VariableExpImpl": 1,
      "PropertyCallExpImpl": 3
    },
    "properties": [
      "operation",
      "symbolName",
      "type"
    ]
  },
  {
    "operations": {},
    "body": "aTrustedFunction.operation.accessVariable.queueType.maxLengthConstant",
    "type": "TemplateInvocationArgument",
    "constructs": {
      "VariableExpImpl": 1,
      "PropertyCallExpImpl": 4
    },
    "properties": [
      "maxLengthConstant",
      "operation",
      "queueType",
      "accessVariable"
    ]
  },
  {
    "operations": {"oclIsKindOf": 1},
    "body": "aTrustedFunction.operation.type.oclIsKindOf(rte::module::UnionType)",
    "type": "IfExpression",
    "constructs": {
      "VariableExpImpl": 1,
      "OperationCallExpImpl": 1,
      "TypeExpImpl": 1,
      "PropertyCallExpImpl": 2
    },
    "properties": [
      "operation",
      "type"
    ]
  },
  {
    "operations": {},
    "body": "aTrustedFunction.operation.accessVariable",
    "type": "TemplateInvocationArgument",
    "constructs": {
      "VariableExpImpl": 1,
      "PropertyCallExpImpl": 2
    },
    "properties": [
      "operation",
      "accessVariable"
    ]
  },
  {
    "operations": {},
    "body": "aTrustedFunction.operation.type.symbolName",
    "type": "TemplateExpression",
    "constructs": {
      "VariableExpImpl": 1,
      "PropertyCallExpImpl": 3
    },
    "properties": [
      "operation",
      "symbolName",
      "type"
    ]
  },
  {
    "operations": {},
    "body": "aTrustedFunction.operation.type.symbolName",
    "type": "TemplateExpression",
    "constructs": {
      "VariableExpImpl": 1,
      "PropertyCallExpImpl": 3
    },
    "properties": [
      "operation",
      "symbolName",
      "type"
    ]
  },
  {
    "operations": {},
    "body": "aTrustedFunction.operation.accessVariable.queueType.maxLengthConstant",
    "type": "TemplateInvocationArgument",
    "constructs": {
      "VariableExpImpl": 1,
      "PropertyCallExpImpl": 4
    },
    "properties": [
      "maxLengthConstant",
      "operation",
      "queueType",
      "accessVariable"
    ]
  },
  {
    "operations": {},
    "body": "aTrustedFunction.operation.accessVariable",
    "type": "TemplateInvocationArgument",
    "constructs": {
      "VariableExpImpl": 1,
      "PropertyCallExpImpl": 2
    },
    "properties": [
      "operation",
      "accessVariable"
    ]
  },
  {
    "operations": {},
    "body": "aTrustedFunction.operation.type.symbolName",
    "type": "TemplateExpression",
    "constructs": {
      "VariableExpImpl": 1,
      "PropertyCallExpImpl": 3
    },
    "properties": [
      "operation",
      "symbolName",
      "type"
    ]
  },
  {
    "operations": {},
    "body": "aTrustedFunction.operation.type.symbolName",
    "type": "TemplateExpression",
    "constructs": {
      "VariableExpImpl": 1,
      "PropertyCallExpImpl": 3
    },
    "properties": [
      "operation",
      "type",
      "symbolName"
    ]
  },
  {
    "operations": {},
    "body": "aTrustedFunction.operation.accessVariable.queueType.maxLengthConstant",
    "type": "TemplateInvocationArgument",
    "constructs": {
      "VariableExpImpl": 1,
      "PropertyCallExpImpl": 4
    },
    "properties": [
      "maxLengthConstant",
      "operation",
      "queueType",
      "accessVariable"
    ]
  },
  {
    "operations": {},
    "body": "aExcludeOperation",
    "type": "TemplateInvocationArgument",
    "constructs": {"VariableExpImpl": 1},
    "properties": []
  },
  {
    "operations": {},
    "body": "aTrustedFunction.returnType.symbolName",
    "type": "TemplateExpression",
    "constructs": {
      "VariableExpImpl": 1,
      "PropertyCallExpImpl": 2
    },
    "properties": [
      "symbolName",
      "returnType"
    ]
  },
  {
    "operations": {},
    "body": "aTrustedFunction.symbolName",
    "type": "TemplateExpression",
    "constructs": {
      "VariableExpImpl": 1,
      "PropertyCallExpImpl": 1
    },
    "properties": ["symbolName"]
  },
  {
    "operations": {},
    "body": "aTrustedFunction",
    "type": "TemplateInvocationArgument",
    "constructs": {"VariableExpImpl": 1},
    "properties": []
  },
  {
    "operations": {},
    "body": "aTrustedFunction.csTfParamTypeName",
    "type": "TemplateExpression",
    "constructs": {
      "VariableExpImpl": 1,
      "PropertyCallExpImpl": 1
    },
    "properties": ["csTfParamTypeName"]
  },
  {
    "operations": {},
    "body": "aTrustedFunction.csTfParamTypeName",
    "type": "TemplateExpression",
    "constructs": {
      "VariableExpImpl": 1,
      "PropertyCallExpImpl": 1
    },
    "properties": ["csTfParamTypeName"]
  },
  {
    "operations": {},
    "body": "aTrustedFunction.csTfCalledRunnable",
    "type": "ForIter",
    "constructs": {
      "VariableExpImpl": 1,
      "PropertyCallExpImpl": 1
    },
    "properties": ["csTfCalledRunnable"]
  },
  {
    "operations": {},
    "body": "aCsTfCalledRunnable.csTfOpidConstantName",
    "type": "TemplateExpression",
    "constructs": {
      "VariableExpImpl": 1,
      "PropertyCallExpImpl": 1
    },
    "properties": ["csTfOpidConstantName"]
  },
  {
    "operations": {},
    "body": "aCsTfCalledRunnable.startOperation.rieaExcludeOperation",
    "type": "ForIter",
    "constructs": {
      "VariableExpImpl": 1,
      "PropertyCallExpImpl": 2
    },
    "properties": [
      "rieaExcludeOperation",
      "startOperation"
    ]
  },
  {
    "operations": {},
    "body": "aExcludeOperation",
    "type": "TemplateInvocationArgument",
    "constructs": {"VariableExpImpl": 1},
    "properties": []
  },
  {
    "operations": {},
    "body": "aCsTfCalledRunnable.startOperation.startServerRunnable.hasReturnValue",
    "type": "IfExpression",
    "constructs": {
      "VariableExpImpl": 1,
      "PropertyCallExpImpl": 3
    },
    "properties": [
      "hasReturnValue",
      "startServerRunnable",
      "startOperation"
    ]
  },
  {
    "operations": {},
    "body": "aCsTfCalledRunnable.startOperation.startServerRunnable.symbolName",
    "type": "TemplateExpression",
    "constructs": {
      "VariableExpImpl": 1,
      "PropertyCallExpImpl": 3
    },
    "properties": [
      "symbolName",
      "startOperation",
      "startServerRunnable"
    ]
  },
  {
    "operations": {},
    "body": "aCsTfCalledRunnable",
    "type": "TemplateInvocationArgument",
    "constructs": {"VariableExpImpl": 1},
    "properties": []
  },
  {
    "operations": {},
    "body": "aCsTfCalledRunnable.startOperation.startServerRunnable.symbolName",
    "type": "TemplateExpression",
    "constructs": {
      "VariableExpImpl": 1,
      "PropertyCallExpImpl": 3
    },
    "properties": [
      "symbolName",
      "startOperation",
      "startServerRunnable"
    ]
  },
  {
    "operations": {},
    "body": "aCsTfCalledRunnable",
    "type": "TemplateInvocationArgument",
    "constructs": {"VariableExpImpl": 1},
    "properties": []
  },
  {
    "operations": {"reverse": 1},
    "body": "aCsTfCalledRunnable.startOperation.rieaExcludeOperation->reverse()",
    "type": "ForIter",
    "constructs": {
      "VariableExpImpl": 1,
      "OperationCallExpImpl": 1,
      "PropertyCallExpImpl": 2
    },
    "properties": [
      "rieaExcludeOperation",
      "startOperation"
    ]
  },
  {
    "operations": {},
    "body": "aExcludeOperation",
    "type": "TemplateInvocationArgument",
    "constructs": {"VariableExpImpl": 1},
    "properties": []
  },
  {
    "operations": {},
    "body": "aRteSource.rteApiGroup",
    "type": "ForIter",
    "constructs": {
      "VariableExpImpl": 1,
      "PropertyCallExpImpl": 1
    },
    "properties": ["rteApiGroup"]
  },
  {
    "operations": {},
    "body": "aGroup.memoryMapping",
    "type": "TemplateInvocationArgument",
    "constructs": {
      "VariableExpImpl": 1,
      "PropertyCallExpImpl": 1
    },
    "properties": ["memoryMapping"]
  },
  {
    "operations": {},
    "body": "aGroup.rteApi",
    "type": "ForIter",
    "constructs": {
      "VariableExpImpl": 1,
      "PropertyCallExpImpl": 1
    },
    "properties": ["rteApi"]
  },
  {
    "operations": {"not": 1},
    "body": "aRteApi.isInline.not()",
    "type": "IfExpression",
    "constructs": {
      "VariableExpImpl": 1,
      "OperationCallExpImpl": 1,
      "PropertyCallExpImpl": 1
    },
    "properties": ["isInline"]
  },
  {
    "operations": {},
    "body": "aRteApi",
    "type": "TemplateInvocationArgument",
    "constructs": {"VariableExpImpl": 1},
    "properties": []
  },
  {
    "operations": {},
    "body": "aGroup.memoryMapping",
    "type": "TemplateInvocationArgument",
    "constructs": {
      "VariableExpImpl": 1,
      "PropertyCallExpImpl": 1
    },
    "properties": ["memoryMapping"]
  },
  {
    "operations": {},
    "body": "aRteSource.comSignalApiWrapperGroup",
    "type": "ForIter",
    "constructs": {
      "VariableExpImpl": 1,
      "PropertyCallExpImpl": 1
    },
    "properties": ["comSignalApiWrapperGroup"]
  },
  {
    "operations": {},
    "body": "aGroup.memoryMapping",
    "type": "TemplateInvocationArgument",
    "constructs": {
      "VariableExpImpl": 1,
      "PropertyCallExpImpl": 1
    },
    "properties": ["memoryMapping"]
  },
  {
    "operations": {},
    "body": "aGroup.comSignalApiWrapper",
    "type": "ForIter",
    "constructs": {
      "VariableExpImpl": 1,
      "PropertyCallExpImpl": 1
    },
    "properties": ["comSignalApiWrapper"]
  },
  {
    "operations": {},
    "body": "aComSignalApiWrapper",
    "type": "TemplateInvocationArgument",
    "constructs": {"VariableExpImpl": 1},
    "properties": []
  },
  {
    "operations": {},
    "body": "aGroup.memoryMapping",
    "type": "TemplateInvocationArgument",
    "constructs": {
      "VariableExpImpl": 1,
      "PropertyCallExpImpl": 1
    },
    "properties": ["memoryMapping"]
  },
  {
    "operations": {},
    "body": "aComSignalApiWrapper.symbolName",
    "type": "TemplateExpression",
    "constructs": {
      "VariableExpImpl": 1,
      "PropertyCallExpImpl": 1
    },
    "properties": ["symbolName"]
  },
  {
    "operations": {},
    "body": "aComSignalApiWrapper",
    "type": "TemplateInvocationArgument",
    "constructs": {"VariableExpImpl": 1},
    "properties": []
  },
  {
    "operations": {},
    "body": "aComSignalApiWrapper.returnType.symbolName",
    "type": "TemplateExpression",
    "constructs": {
      "VariableExpImpl": 1,
      "PropertyCallExpImpl": 2
    },
    "properties": [
      "symbolName",
      "returnType"
    ]
  },
  {
    "operations": {},
    "body": "aComSignalApiWrapper.returnType.symbolName",
    "type": "TemplateExpression",
    "constructs": {
      "VariableExpImpl": 1,
      "PropertyCallExpImpl": 2
    },
    "properties": [
      "symbolName",
      "returnType"
    ]
  },
  {
    "operations": {},
    "body": "aComSignalApiWrapper.signalGroupSymbolName",
    "type": "TemplateExpression",
    "constructs": {
      "VariableExpImpl": 1,
      "PropertyCallExpImpl": 1
    },
    "properties": ["signalGroupSymbolName"]
  },
  {
    "operations": {"at": 1},
    "body": "aComSignalApiWrapper.param->at(1).symbolName",
    "type": "TemplateExpression",
    "constructs": {
      "VariableExpImpl": 1,
      "OperationCallExpImpl": 1,
      "IntegerLiteralExpImpl": 1,
      "PropertyCallExpImpl": 2
    },
    "properties": [
      "param",
      "symbolName"
    ]
  },
  {
    "operations": {"at": 1},
    "body": "aComSignalApiWrapper.param->at(1).symbolName",
    "type": "TemplateExpression",
    "constructs": {
      "OperationCallExpImpl": 1,
      "VariableExpImpl": 1,
      "IntegerLiteralExpImpl": 1,
      "PropertyCallExpImpl": 2
    },
    "properties": [
      "param",
      "symbolName"
    ]
  },
  {
    "operations": {},
    "body": "aComSignalApiWrapper.signalSymbolName",
    "type": "TemplateExpression",
    "constructs": {
      "VariableExpImpl": 1,
      "PropertyCallExpImpl": 1
    },
    "properties": ["signalSymbolName"]
  },
  {
    "operations": {"at": 1},
    "body": "aComSignalApiWrapper.param->at(1).symbolName",
    "type": "TemplateExpression",
    "constructs": {
      "OperationCallExpImpl": 1,
      "VariableExpImpl": 1,
      "IntegerLiteralExpImpl": 1,
      "PropertyCallExpImpl": 2
    },
    "properties": [
      "param",
      "symbolName"
    ]
  },
  {
    "operations": {"at": 1},
    "body": "aComSignalApiWrapper.param->at(2).symbolName",
    "type": "TemplateExpression",
    "constructs": {
      "OperationCallExpImpl": 1,
      "VariableExpImpl": 1,
      "IntegerLiteralExpImpl": 1,
      "PropertyCallExpImpl": 2
    },
    "properties": [
      "param",
      "symbolName"
    ]
  },
  {
    "operations": {"at": 1},
    "body": "aComSignalApiWrapper.param->at(1).symbolName",
    "type": "TemplateExpression",
    "constructs": {
      "VariableExpImpl": 1,
      "OperationCallExpImpl": 1,
      "IntegerLiteralExpImpl": 1,
      "PropertyCallExpImpl": 2
    },
    "properties": [
      "param",
      "symbolName"
    ]
  },
  {
    "operations": {},
    "body": "aComSignalApiWrapper.symbolName",
    "type": "TemplateExpression",
    "constructs": {
      "VariableExpImpl": 1,
      "PropertyCallExpImpl": 1
    },
    "properties": ["symbolName"]
  },
  {
    "operations": {},
    "body": "aComSignalApiWrapper",
    "type": "TemplateInvocationArgument",
    "constructs": {"VariableExpImpl": 1},
    "properties": []
  },
  {
    "operations": {"at": 1},
    "body": "aComSignalApiWrapper.param->at(1).symbolName",
    "type": "TemplateExpression",
    "constructs": {
      "OperationCallExpImpl": 1,
      "VariableExpImpl": 1,
      "IntegerLiteralExpImpl": 1,
      "PropertyCallExpImpl": 2
    },
    "properties": [
      "param",
      "symbolName"
    ]
  },
  {
    "operations": {},
    "body": "aComSignalApiWrapper.signalSymbolName",
    "type": "TemplateExpression",
    "constructs": {
      "VariableExpImpl": 1,
      "PropertyCallExpImpl": 1
    },
    "properties": ["signalSymbolName"]
  },
  {
    "operations": {"at": 1},
    "body": "aComSignalApiWrapper.param->at(1).symbolName",
    "type": "TemplateExpression",
    "constructs": {
      "VariableExpImpl": 1,
      "OperationCallExpImpl": 1,
      "IntegerLiteralExpImpl": 1,
      "PropertyCallExpImpl": 2
    },
    "properties": [
      "param",
      "symbolName"
    ]
  },
  {
    "operations": {"at": 1},
    "body": "aComSignalApiWrapper.param->at(2).symbolName",
    "type": "TemplateExpression",
    "constructs": {
      "OperationCallExpImpl": 1,
      "VariableExpImpl": 1,
      "IntegerLiteralExpImpl": 1,
      "PropertyCallExpImpl": 2
    },
    "properties": [
      "param",
      "symbolName"
    ]
  },
  {
    "operations": {"at": 1},
    "body": "aComSignalApiWrapper.param->at(1).symbolName",
    "type": "TemplateExpression",
    "constructs": {
      "OperationCallExpImpl": 1,
      "VariableExpImpl": 1,
      "IntegerLiteralExpImpl": 1,
      "PropertyCallExpImpl": 2
    },
    "properties": [
      "param",
      "symbolName"
    ]
  },
  {
    "operations": {},
    "body": "aComSignalApiWrapper.signalGroupSymbolName",
    "type": "TemplateExpression",
    "constructs": {
      "VariableExpImpl": 1,
      "PropertyCallExpImpl": 1
    },
    "properties": ["signalGroupSymbolName"]
  },
  {
    "operations": {"at": 1},
    "body": "aComSignalApiWrapper.param->at(1).symbolName",
    "type": "TemplateExpression",
    "constructs": {
      "OperationCallExpImpl": 1,
      "VariableExpImpl": 1,
      "IntegerLiteralExpImpl": 1,
      "PropertyCallExpImpl": 2
    },
    "properties": [
      "param",
      "symbolName"
    ]
  },
  {
    "operations": {},
    "body": "aRteSource.comProxyFunctionGroup",
    "type": "ForIter",
    "constructs": {
      "VariableExpImpl": 1,
      "PropertyCallExpImpl": 1
    },
    "properties": ["comProxyFunctionGroup"]
  },
  {
    "operations": {},
    "body": "aGroup.memoryMapping",
    "type": "TemplateInvocationArgument",
    "constructs": {
      "VariableExpImpl": 1,
      "PropertyCallExpImpl": 1
    },
    "properties": ["memoryMapping"]
  },
  {
    "operations": {},
    "body": "aGroup.comProxyFunction",
    "type": "ForIter",
    "constructs": {
      "VariableExpImpl": 1,
      "PropertyCallExpImpl": 1
    },
    "properties": ["comProxyFunction"]
  },
  {
    "operations": {},
    "body": "aComProxyFunction",
    "type": "TemplateInvocationArgument",
    "constructs": {"VariableExpImpl": 1},
    "properties": []
  },
  {
    "operations": {},
    "body": "aGroup.memoryMapping",
    "type": "TemplateInvocationArgument",
    "constructs": {
      "VariableExpImpl": 1,
      "PropertyCallExpImpl": 1
    },
    "properties": ["memoryMapping"]
  },
  {
    "operations": {},
    "body": "aComProxyFunction.symbolName",
    "type": "TemplateExpression",
    "constructs": {
      "VariableExpImpl": 1,
      "PropertyCallExpImpl": 1
    },
    "properties": ["symbolName"]
  },
  {
    "operations": {},
    "body": "aComProxyFunction",
    "type": "TemplateInvocationArgument",
    "constructs": {"VariableExpImpl": 1},
    "properties": []
  },
  {
    "operations": {},
    "body": "aComProxyFunction.iocReceiveSymbolName",
    "type": "TemplateExpression",
    "constructs": {
      "VariableExpImpl": 1,
      "PropertyCallExpImpl": 1
    },
    "properties": ["iocReceiveSymbolName"]
  },
  {
    "operations": {},
    "body": "aComProxyFunction.bufferVariable",
    "type": "TemplateInvocationArgument",
    "constructs": {
      "VariableExpImpl": 1,
      "PropertyCallExpImpl": 1
    },
    "properties": ["bufferVariable"]
  },
  {
    "operations": {"oclIsUndefined": 1},
    "body": "aComProxyFunction.tAckStatus.oclIsUndefined()",
    "type": "IfExpression",
    "constructs": {
      "OperationCallExpImpl": 1,
      "VariableExpImpl": 1,
      "PropertyCallExpImpl": 1
    },
    "properties": ["tAckStatus"]
  },
  {
    "operations": {},
    "body": "aComProxyFunction.isGroup",
    "type": "IfExpression",
    "constructs": {
      "VariableExpImpl": 1,
      "PropertyCallExpImpl": 1
    },
    "properties": ["isGroup"]
  },
  {
    "operations": {},
    "body": "aComProxyFunction.sendSignalFunctionSymbolName",
    "type": "TemplateExpression",
    "constructs": {
      "VariableExpImpl": 1,
      "PropertyCallExpImpl": 1
    },
    "properties": ["sendSignalFunctionSymbolName"]
  },
  {
    "operations": {},
    "body": "aComProxyFunction.signalInformationSymbolName",
    "type": "TemplateExpression",
    "constructs": {
      "VariableExpImpl": 1,
      "PropertyCallExpImpl": 1
    },
    "properties": ["signalInformationSymbolName"]
  },
  {
    "operations": {},
    "body": "aComProxyFunction.bufferVariable",
    "type": "TemplateInvocationArgument",
    "constructs": {
      "VariableExpImpl": 1,
      "PropertyCallExpImpl": 1
    },
    "properties": ["bufferVariable"]
  },
  {
    "operations": {},
    "body": "aComProxyFunction.sendSignalFunctionSymbolName",
    "type": "TemplateExpression",
    "constructs": {
      "VariableExpImpl": 1,
      "PropertyCallExpImpl": 1
    },
    "properties": ["sendSignalFunctionSymbolName"]
  },
  {
    "operations": {},
    "body": "aComProxyFunction.signalInformationSymbolName",
    "type": "TemplateExpression",
    "constructs": {
      "VariableExpImpl": 1,
      "PropertyCallExpImpl": 1
    },
    "properties": ["signalInformationSymbolName"]
  },
  {
    "operations": {},
    "body": "aComProxyFunction.bufferVariable",
    "type": "TemplateInvocationArgument",
    "constructs": {
      "VariableExpImpl": 1,
      "PropertyCallExpImpl": 1
    },
    "properties": ["bufferVariable"]
  },
  {
    "operations": {},
    "body": "aComProxyFunction.tAckStatus.statusVariable.symbolName",
    "type": "TemplateExpression",
    "constructs": {
      "VariableExpImpl": 1,
      "PropertyCallExpImpl": 3
    },
    "properties": [
      "tAckStatus",
      "statusVariable",
      "symbolName"
    ]
  },
  {
    "operations": {},
    "body": "aComProxyFunction.tAckStatus.statusVariable.symbolName",
    "type": "TemplateExpression",
    "constructs": {
      "VariableExpImpl": 1,
      "PropertyCallExpImpl": 3
    },
    "properties": [
      "tAckStatus",
      "statusVariable",
      "symbolName"
    ]
  },
  {
    "operations": {},
    "body": "aComProxyFunction",
    "type": "TemplateInvocationArgument",
    "constructs": {"VariableExpImpl": 1},
    "properties": []
  },
  {
    "operations": {},
    "body": "aComProxyFunction.isGroup",
    "type": "IfExpression",
    "constructs": {
      "VariableExpImpl": 1,
      "PropertyCallExpImpl": 1
    },
    "properties": ["isGroup"]
  },
  {
    "operations": {},
    "body": "aComProxyFunction.sendSignalFunctionSymbolName",
    "type": "TemplateExpression",
    "constructs": {
      "VariableExpImpl": 1,
      "PropertyCallExpImpl": 1
    },
    "properties": ["sendSignalFunctionSymbolName"]
  },
  {
    "operations": {},
    "body": "aComProxyFunction.signalInformationSymbolName",
    "type": "TemplateExpression",
    "constructs": {
      "VariableExpImpl": 1,
      "PropertyCallExpImpl": 1
    },
    "properties": ["signalInformationSymbolName"]
  },
  {
    "operations": {},
    "body": "aComProxyFunction.bufferVariable",
    "type": "TemplateInvocationArgument",
    "constructs": {
      "VariableExpImpl": 1,
      "PropertyCallExpImpl": 1
    },
    "properties": ["bufferVariable"]
  },
  {
    "operations": {},
    "body": "aComProxyFunction.sendSignalFunctionSymbolName",
    "type": "TemplateExpression",
    "constructs": {
      "VariableExpImpl": 1,
      "PropertyCallExpImpl": 1
    },
    "properties": ["sendSignalFunctionSymbolName"]
  },
  {
    "operations": {},
    "body": "aComProxyFunction.signalInformationSymbolName",
    "type": "TemplateExpression",
    "constructs": {
      "VariableExpImpl": 1,
      "PropertyCallExpImpl": 1
    },
    "properties": ["signalInformationSymbolName"]
  },
  {
    "operations": {},
    "body": "aComProxyFunction.bufferVariable",
    "type": "TemplateInvocationArgument",
    "constructs": {
      "VariableExpImpl": 1,
      "PropertyCallExpImpl": 1
    },
    "properties": ["bufferVariable"]
  },
  {
    "operations": {},
    "body": "aRteSource.comCallbackGroup",
    "type": "ForIter",
    "constructs": {
      "VariableExpImpl": 1,
      "PropertyCallExpImpl": 1
    },
    "properties": ["comCallbackGroup"]
  },
  {
    "operations": {},
    "body": "aGroup.memoryMapping",
    "type": "TemplateInvocationArgument",
    "constructs": {
      "VariableExpImpl": 1,
      "PropertyCallExpImpl": 1
    },
    "properties": ["memoryMapping"]
  },
  {
    "operations": {},
    "body": "aGroup.comCallback",
    "type": "ForIter",
    "constructs": {
      "VariableExpImpl": 1,
      "PropertyCallExpImpl": 1
    },
    "properties": ["comCallback"]
  },
  {
    "operations": {},
    "body": "aComCallback",
    "type": "TemplateInvocationArgument",
    "constructs": {"VariableExpImpl": 1},
    "properties": []
  },
  {
    "operations": {},
    "body": "aGroup.memoryMapping",
    "type": "TemplateInvocationArgument",
    "constructs": {
      "VariableExpImpl": 1,
      "PropertyCallExpImpl": 1
    },
    "properties": ["memoryMapping"]
  },
  {
    "operations": {"isEmpty": 1},
    "body": "aComCallback.operation->isEmpty()",
    "type": "TemplateGuard",
    "constructs": {
      "OperationCallExpImpl": 1,
      "VariableExpImpl": 1,
      "PropertyCallExpImpl": 1
    },
    "properties": ["operation"]
  },
  {
    "operations": {},
    "body": "aComCallback.returnType.symbolName",
    "type": "TemplateExpression",
    "constructs": {
      "VariableExpImpl": 1,
      "PropertyCallExpImpl": 2
    },
    "properties": [
      "symbolName",
      "returnType"
    ]
  },
  {
    "operations": {},
    "body": "aComCallback.symbolName",
    "type": "TemplateExpression",
    "constructs": {
      "VariableExpImpl": 1,
      "PropertyCallExpImpl": 1
    },
    "properties": ["symbolName"]
  },
  {
    "operations": {},
    "body": "aComCallback",
    "type": "TemplateInvocationArgument",
    "constructs": {"VariableExpImpl": 1},
    "properties": []
  },
  {
    "operations": {},
    "body": "aComCallback",
    "type": "TemplateInvocationArgument",
    "constructs": {"VariableExpImpl": 1},
    "properties": []
  },
  {
    "operations": {
      "not": 1,
      "isEmpty": 1
    },
    "body": "aComCallback.operation->isEmpty().not()",
    "type": "TemplateGuard",
    "constructs": {
      "OperationCallExpImpl": 2,
      "VariableExpImpl": 1,
      "PropertyCallExpImpl": 1
    },
    "properties": ["operation"]
  },
  {
    "operations": {},
    "body": "aComCallback.returnType.symbolName",
    "type": "TemplateExpression",
    "constructs": {
      "VariableExpImpl": 1,
      "PropertyCallExpImpl": 2
    },
    "properties": [
      "symbolName",
      "returnType"
    ]
  },
  {
    "operations": {},
    "body": "aComCallback.symbolName",
    "type": "TemplateExpression",
    "constructs": {
      "VariableExpImpl": 1,
      "PropertyCallExpImpl": 1
    },
    "properties": ["symbolName"]
  },
  {
    "operations": {},
    "body": "aComCallback",
    "type": "TemplateInvocationArgument",
    "constructs": {"VariableExpImpl": 1},
    "properties": []
  },
  {
    "operations": {},
    "body": "aComCallback",
    "type": "TemplateInvocationArgument",
    "constructs": {"VariableExpImpl": 1},
    "properties": []
  },
  {
    "operations": {},
    "body": "aComCallback",
    "type": "TemplateInvocationArgument",
    "constructs": {"VariableExpImpl": 1},
    "properties": []
  },
  {
    "operations": {
      "or": 1,
      "oclIsKindOf": 2
    },
    "body": "aComCallback.dataVariable.type.oclIsKindOf(rte::module::StructType).or(aComCallback.dataVariable.type.oclIsKindOf(rte::module::UnionType))",
    "type": "IfExpression",
    "constructs": {
      "OperationCallExpImpl": 3,
      "VariableExpImpl": 2,
      "TypeExpImpl": 2,
      "PropertyCallExpImpl": 4
    },
    "properties": [
      "dataVariable",
      "type"
    ]
  },
  {
    "operations": {},
    "body": "aComCallback.accessApi.symbolName",
    "type": "TemplateExpression",
    "constructs": {
      "VariableExpImpl": 1,
      "PropertyCallExpImpl": 2
    },
    "properties": [
      "symbolName",
      "accessApi"
    ]
  },
  {
    "operations": {},
    "body": "aComCallback.accessApi.isSignalGroup",
    "type": "IfExpression",
    "constructs": {
      "VariableExpImpl": 1,
      "PropertyCallExpImpl": 2
    },
    "properties": [
      "accessApi",
      "isSignalGroup"
    ]
  },
  {
    "operations": {},
    "body": "aComCallback.accessApi.comSignalSymbolName",
    "type": "TemplateExpression",
    "constructs": {
      "VariableExpImpl": 1,
      "PropertyCallExpImpl": 2
    },
    "properties": [
      "accessApi",
      "comSignalSymbolName"
    ]
  },
  {
    "operations": {},
    "body": "aComCallback.accessApi.isSignalGroup",
    "type": "IfExpression",
    "constructs": {
      "VariableExpImpl": 1,
      "PropertyCallExpImpl": 2
    },
    "properties": [
      "accessApi",
      "isSignalGroup"
    ]
  },
  {
    "operations": {},
    "body": "aComCallback.dataVariable",
    "type": "TemplateInvocationArgument",
    "constructs": {
      "VariableExpImpl": 1,
      "PropertyCallExpImpl": 1
    },
    "properties": ["dataVariable"]
  },
  {
    "operations": {},
    "body": "aComCallback.accessApi.symbolName",
    "type": "TemplateExpression",
    "constructs": {
      "VariableExpImpl": 1,
      "PropertyCallExpImpl": 2
    },
    "properties": [
      "symbolName",
      "accessApi"
    ]
  },
  {
    "operations": {},
    "body": "aComCallback.accessApi.comSignalSymbolName",
    "type": "TemplateExpression",
    "constructs": {
      "VariableExpImpl": 1,
      "PropertyCallExpImpl": 2
    },
    "properties": [
      "accessApi",
      "comSignalSymbolName"
    ]
  },
  {
    "operations": {},
    "body": "aComCallback.dataVariable",
    "type": "TemplateInvocationArgument",
    "constructs": {
      "VariableExpImpl": 1,
      "PropertyCallExpImpl": 1
    },
    "properties": ["dataVariable"]
  },
  {
    "operations": {},
    "body": "aComCallback.operation",
    "type": "ForIter",
    "constructs": {
      "VariableExpImpl": 1,
      "PropertyCallExpImpl": 1
    },
    "properties": ["operation"]
  },
  {
    "operations": {},
    "body": "aSendOperation",
    "type": "TemplateInvocationArgument",
    "constructs": {"VariableExpImpl": 1},
    "properties": []
  },
  {
    "operations": {},
    "body": "aComCallback",
    "type": "TemplateInvocationArgument",
    "constructs": {"VariableExpImpl": 1},
    "properties": []
  },
  {
    "operations": {},
    "body": "aComCallback.returnType.symbolName",
    "type": "TemplateExpression",
    "constructs": {
      "VariableExpImpl": 1,
      "PropertyCallExpImpl": 2
    },
    "properties": [
      "symbolName",
      "returnType"
    ]
  },
  {
    "operations": {},
    "body": "aComCallback.symbolName",
    "type": "TemplateExpression",
    "constructs": {
      "VariableExpImpl": 1,
      "PropertyCallExpImpl": 1
    },
    "properties": ["symbolName"]
  },
  {
    "operations": {},
    "body": "aComCallback",
    "type": "TemplateInvocationArgument",
    "constructs": {"VariableExpImpl": 1},
    "properties": []
  },
  {
    "operations": {},
    "body": "aComCallback",
    "type": "TemplateInvocationArgument",
    "constructs": {"VariableExpImpl": 1},
    "properties": []
  },
  {
    "operations": {},
    "body": "aComCallback",
    "type": "TemplateInvocationArgument",
    "constructs": {"VariableExpImpl": 1},
    "properties": []
  },
  {
    "operations": {
      "or": 1,
      "oclIsKindOf": 2
    },
    "body": "aComCallback.dataVariable.type.oclIsKindOf(rte::module::StructType).or(aComCallback.dataVariable.type.oclIsKindOf(rte::module::UnionType))",
    "type": "IfExpression",
    "constructs": {
      "VariableExpImpl": 2,
      "OperationCallExpImpl": 3,
      "TypeExpImpl": 2,
      "PropertyCallExpImpl": 4
    },
    "properties": [
      "dataVariable",
      "type"
    ]
  },
  {
    "operations": {},
    "body": "aComCallback.accessApi.symbolName",
    "type": "TemplateExpression",
    "constructs": {
      "VariableExpImpl": 1,
      "PropertyCallExpImpl": 2
    },
    "properties": [
      "symbolName",
      "accessApi"
    ]
  },
  {
    "operations": {},
    "body": "aComCallback.accessApi.isSignalGroup",
    "type": "IfExpression",
    "constructs": {
      "VariableExpImpl": 1,
      "PropertyCallExpImpl": 2
    },
    "properties": [
      "accessApi",
      "isSignalGroup"
    ]
  },
  {
    "operations": {},
    "body": "aComCallback.accessApi.comSignalSymbolName",
    "type": "TemplateExpression",
    "constructs": {
      "VariableExpImpl": 1,
      "PropertyCallExpImpl": 2
    },
    "properties": [
      "accessApi",
      "comSignalSymbolName"
    ]
  },
  {
    "operations": {},
    "body": "aComCallback.accessApi.isSignalGroup",
    "type": "IfExpression",
    "constructs": {
      "VariableExpImpl": 1,
      "PropertyCallExpImpl": 2
    },
    "properties": [
      "accessApi",
      "isSignalGroup"
    ]
  },
  {
    "operations": {},
    "body": "aComCallback.dataVariable",
    "type": "TemplateInvocationArgument",
    "constructs": {
      "VariableExpImpl": 1,
      "PropertyCallExpImpl": 1
    },
    "properties": ["dataVariable"]
  },
  {
    "operations": {},
    "body": "aComCallback.accessApi.symbolName",
    "type": "TemplateExpression",
    "constructs": {
      "VariableExpImpl": 1,
      "PropertyCallExpImpl": 2
    },
    "properties": [
      "symbolName",
      "accessApi"
    ]
  },
  {
    "operations": {},
    "body": "aComCallback.accessApi.comSignalSymbolName",
    "type": "TemplateExpression",
    "constructs": {
      "VariableExpImpl": 1,
      "PropertyCallExpImpl": 2
    },
    "properties": [
      "accessApi",
      "comSignalSymbolName"
    ]
  },
  {
    "operations": {},
    "body": "aComCallback.dataVariable",
    "type": "TemplateInvocationArgument",
    "constructs": {
      "VariableExpImpl": 1,
      "PropertyCallExpImpl": 1
    },
    "properties": ["dataVariable"]
  },
  {
    "operations": {},
    "body": "aComCallback.operation",
    "type": "ForIter",
    "constructs": {
      "VariableExpImpl": 1,
      "PropertyCallExpImpl": 1
    },
    "properties": ["operation"]
  },
  {
    "operations": {},
    "body": "aSendOperation",
    "type": "TemplateInvocationArgument",
    "constructs": {"VariableExpImpl": 1},
    "properties": []
  },
  {
    "operations": {},
    "body": "aComCallback",
    "type": "TemplateInvocationArgument",
    "constructs": {"VariableExpImpl": 1},
    "properties": []
  },
  {
    "operations": {},
    "body": "aComCallback.returnType.symbolName",
    "type": "TemplateExpression",
    "constructs": {
      "VariableExpImpl": 1,
      "PropertyCallExpImpl": 2
    },
    "properties": [
      "symbolName",
      "returnType"
    ]
  },
  {
    "operations": {},
    "body": "aComCallback.symbolName",
    "type": "TemplateExpression",
    "constructs": {
      "VariableExpImpl": 1,
      "PropertyCallExpImpl": 1
    },
    "properties": ["symbolName"]
  },
  {
    "operations": {},
    "body": "aComCallback",
    "type": "TemplateInvocationArgument",
    "constructs": {"VariableExpImpl": 1},
    "properties": []
  },
  {
    "operations": {},
    "body": "aComCallback",
    "type": "TemplateInvocationArgument",
    "constructs": {"VariableExpImpl": 1},
    "properties": []
  },
  {
    "operations": {},
    "body": "aComCallback",
    "type": "TemplateInvocationArgument",
    "constructs": {"VariableExpImpl": 1},
    "properties": []
  },
  {
    "operations": {},
    "body": "aComCallback.operation",
    "type": "ForIter",
    "constructs": {
      "VariableExpImpl": 1,
      "PropertyCallExpImpl": 1
    },
    "properties": ["operation"]
  },
  {
    "operations": {},
    "body": "aSendOperation",
    "type": "TemplateInvocationArgument",
    "constructs": {"VariableExpImpl": 1},
    "properties": []
  },
  {
    "operations": {},
    "body": "aComCallback",
    "type": "TemplateInvocationArgument",
    "constructs": {"VariableExpImpl": 1},
    "properties": []
  },
  {
    "operations": {},
    "body": "aComCallback.returnType.symbolName",
    "type": "TemplateExpression",
    "constructs": {
      "VariableExpImpl": 1,
      "PropertyCallExpImpl": 2
    },
    "properties": [
      "symbolName",
      "returnType"
    ]
  },
  {
    "operations": {},
    "body": "aComCallback.symbolName",
    "type": "TemplateExpression",
    "constructs": {
      "VariableExpImpl": 1,
      "PropertyCallExpImpl": 1
    },
    "properties": ["symbolName"]
  },
  {
    "operations": {},
    "body": "aComCallback",
    "type": "TemplateInvocationArgument",
    "constructs": {"VariableExpImpl": 1},
    "properties": []
  },
  {
    "operations": {},
    "body": "aComCallback.tAckNotifyOperation",
    "type": "ForIter",
    "constructs": {
      "VariableExpImpl": 1,
      "PropertyCallExpImpl": 1
    },
    "properties": ["tAckNotifyOperation"]
  },
  {
    "operations": {},
    "body": "tAckNotifyOperation.tAckStatus.statusVariable.symbolName",
    "type": "TemplateExpression",
    "constructs": {
      "VariableExpImpl": 1,
      "PropertyCallExpImpl": 3
    },
    "properties": [
      "tAckStatus",
      "symbolName",
      "statusVariable"
    ]
  },
  {
    "operations": {},
    "body": "tAckNotifyOperation.tAckStatus.statusVariable.symbolName",
    "type": "TemplateExpression",
    "constructs": {
      "VariableExpImpl": 1,
      "PropertyCallExpImpl": 3
    },
    "properties": [
      "tAckStatus",
      "symbolName",
      "statusVariable"
    ]
  },
  {
    "operations": {},
    "body": "tAckNotifyOperation",
    "type": "TemplateInvocationArgument",
    "constructs": {"VariableExpImpl": 1},
    "properties": []
  },
  {
    "operations": {},
    "body": "aComCallback.returnType.symbolName",
    "type": "TemplateExpression",
    "constructs": {
      "VariableExpImpl": 1,
      "PropertyCallExpImpl": 2
    },
    "properties": [
      "symbolName",
      "returnType"
    ]
  },
  {
    "operations": {},
    "body": "aComCallback.symbolName",
    "type": "TemplateExpression",
    "constructs": {
      "VariableExpImpl": 1,
      "PropertyCallExpImpl": 1
    },
    "properties": ["symbolName"]
  },
  {
    "operations": {},
    "body": "aComCallback",
    "type": "TemplateInvocationArgument",
    "constructs": {"VariableExpImpl": 1},
    "properties": []
  },
  {
    "operations": {},
    "body": "aComCallback.tAckNotifyOperation",
    "type": "ForIter",
    "constructs": {
      "VariableExpImpl": 1,
      "PropertyCallExpImpl": 1
    },
    "properties": ["tAckNotifyOperation"]
  },
  {
    "operations": {},
    "body": "tAckNotifyOperation.tAckStatus.statusVariable.symbolName",
    "type": "TemplateExpression",
    "constructs": {
      "VariableExpImpl": 1,
      "PropertyCallExpImpl": 3
    },
    "properties": [
      "tAckStatus",
      "symbolName",
      "statusVariable"
    ]
  },
  {
    "operations": {},
    "body": "tAckNotifyOperation.tAckStatus.statusVariable.symbolName",
    "type": "TemplateExpression",
    "constructs": {
      "VariableExpImpl": 1,
      "PropertyCallExpImpl": 3
    },
    "properties": [
      "tAckStatus",
      "symbolName",
      "statusVariable"
    ]
  },
  {
    "operations": {},
    "body": "tAckNotifyOperation",
    "type": "TemplateInvocationArgument",
    "constructs": {"VariableExpImpl": 1},
    "properties": []
  },
  {
    "operations": {},
    "body": "aComCallback.returnType.symbolName",
    "type": "TemplateExpression",
    "constructs": {
      "VariableExpImpl": 1,
      "PropertyCallExpImpl": 2
    },
    "properties": [
      "symbolName",
      "returnType"
    ]
  },
  {
    "operations": {},
    "body": "aComCallback.symbolName",
    "type": "TemplateExpression",
    "constructs": {
      "VariableExpImpl": 1,
      "PropertyCallExpImpl": 1
    },
    "properties": ["symbolName"]
  },
  {
    "operations": {},
    "body": "aComCallback",
    "type": "TemplateInvocationArgument",
    "constructs": {"VariableExpImpl": 1},
    "properties": []
  },
  {
    "operations": {},
    "body": "aComCallback.tAckNotifyOperation",
    "type": "ForIter",
    "constructs": {
      "VariableExpImpl": 1,
      "PropertyCallExpImpl": 1
    },
    "properties": ["tAckNotifyOperation"]
  },
  {
    "operations": {},
    "body": "tAckNotifyOperation.tAckStatus.statusVariable.symbolName",
    "type": "TemplateExpression",
    "constructs": {
      "VariableExpImpl": 1,
      "PropertyCallExpImpl": 3
    },
    "properties": [
      "tAckStatus",
      "symbolName",
      "statusVariable"
    ]
  },
  {
    "operations": {},
    "body": "tAckNotifyOperation.tAckStatus.statusVariable.symbolName",
    "type": "TemplateExpression",
    "constructs": {
      "VariableExpImpl": 1,
      "PropertyCallExpImpl": 3
    },
    "properties": [
      "tAckStatus",
      "statusVariable",
      "symbolName"
    ]
  },
  {
    "operations": {},
    "body": "tAckNotifyOperation",
    "type": "TemplateInvocationArgument",
    "constructs": {"VariableExpImpl": 1},
    "properties": []
  },
  {
    "operations": {},
    "body": "aRteSource.schmApiGroup",
    "type": "ForIter",
    "constructs": {
      "VariableExpImpl": 1,
      "PropertyCallExpImpl": 1
    },
    "properties": ["schmApiGroup"]
  },
  {
    "operations": {},
    "body": "aGroup.memoryMapping",
    "type": "TemplateInvocationArgument",
    "constructs": {
      "VariableExpImpl": 1,
      "PropertyCallExpImpl": 1
    },
    "properties": ["memoryMapping"]
  },
  {
    "operations": {},
    "body": "aGroup.schmApi",
    "type": "ForIter",
    "constructs": {
      "VariableExpImpl": 1,
      "PropertyCallExpImpl": 1
    },
    "properties": ["schmApi"]
  },
  {
    "operations": {},
    "body": "aSchmApi",
    "type": "TemplateInvocationArgument",
    "constructs": {"VariableExpImpl": 1},
    "properties": []
  },
  {
    "operations": {},
    "body": "aGroup.memoryMapping",
    "type": "TemplateInvocationArgument",
    "constructs": {
      "VariableExpImpl": 1,
      "PropertyCallExpImpl": 1
    },
    "properties": ["memoryMapping"]
  },
  {
    "operations": {},
    "body": "aRteSource.bswSchedulableEntityGroup",
    "type": "ForIter",
    "constructs": {
      "VariableExpImpl": 1,
      "PropertyCallExpImpl": 1
    },
    "properties": ["bswSchedulableEntityGroup"]
  },
  {
    "operations": {},
    "body": "aGroup.memoryMapping",
    "type": "TemplateInvocationArgument",
    "constructs": {
      "VariableExpImpl": 1,
      "PropertyCallExpImpl": 1
    },
    "properties": ["memoryMapping"]
  },
  {
    "operations": {},
    "body": "aGroup.bswSchedulableEntity",
    "type": "ForIter",
    "constructs": {
      "VariableExpImpl": 1,
      "PropertyCallExpImpl": 1
    },
    "properties": ["bswSchedulableEntity"]
  },
  {
    "operations": {},
    "body": "aBswSchedulableEntity",
    "type": "TemplateInvocationArgument",
    "constructs": {"VariableExpImpl": 1},
    "properties": []
  },
  {
    "operations": {},
    "body": "aGroup.memoryMapping",
    "type": "TemplateInvocationArgument",
    "constructs": {
      "VariableExpImpl": 1,
      "PropertyCallExpImpl": 1
    },
    "properties": ["memoryMapping"]
  },
  {
    "operations": {},
    "body": "aBswSchedulableEntity.returnType.symbolName",
    "type": "TemplateExpression",
    "constructs": {
      "VariableExpImpl": 1,
      "PropertyCallExpImpl": 2
    },
    "properties": [
      "symbolName",
      "returnType"
    ]
  },
  {
    "operations": {},
    "body": "aBswSchedulableEntity.symbolName",
    "type": "TemplateExpression",
    "constructs": {
      "VariableExpImpl": 1,
      "PropertyCallExpImpl": 1
    },
    "properties": ["symbolName"]
  },
  {
    "operations": {},
    "body": "aBswSchedulableEntity",
    "type": "TemplateInvocationArgument",
    "constructs": {"VariableExpImpl": 1},
    "properties": []
  },
  {
    "operations": {},
    "body": "aBswSchedulableEntity",
    "type": "TemplateInvocationArgument",
    "constructs": {"VariableExpImpl": 1},
    "properties": []
  },
  {
    "operations": {},
    "body": "aBswSchedulableEntity",
    "type": "TemplateInvocationArgument",
    "constructs": {"VariableExpImpl": 1},
    "properties": []
  },
  {
    "operations": {},
    "body": "aBswSchedulableEntity.operation",
    "type": "ForIter",
    "constructs": {
      "VariableExpImpl": 1,
      "PropertyCallExpImpl": 1
    },
    "properties": ["operation"]
  },
  {
    "operations": {},
    "body": "aProxyOperation.accessApi.symbolName",
    "type": "TemplateExpression",
    "constructs": {
      "VariableExpImpl": 1,
      "PropertyCallExpImpl": 2
    },
    "properties": [
      "accessApi",
      "symbolName"
    ]
  },
  {
    "operations": {},
    "body": "aProxyOperation.tableIndexVariable",
    "type": "TemplateInvocationArgument",
    "constructs": {
      "VariableExpImpl": 1,
      "PropertyCallExpImpl": 1
    },
    "properties": ["tableIndexVariable"]
  },
  {
    "operations": {},
    "body": "aProxyOperation.functionTableSymbolName",
    "type": "TemplateExpression",
    "constructs": {
      "VariableExpImpl": 1,
      "PropertyCallExpImpl": 1
    },
    "properties": ["functionTableSymbolName"]
  },
  {
    "operations": {},
    "body": "aProxyOperation.tableIndexVariable.symbolName",
    "type": "TemplateExpression",
    "constructs": {
      "VariableExpImpl": 1,
      "PropertyCallExpImpl": 2
    },
    "properties": [
      "symbolName",
      "tableIndexVariable"
    ]
  },
  {
    "operations": {"notEmpty": 1},
    "body": "aRteSource.dependentExternalExecutableEntityGroup->notEmpty()",
    "type": "IfExpression",
    "constructs": {
      "VariableExpImpl": 1,
      "OperationCallExpImpl": 1,
      "PropertyCallExpImpl": 1
    },
    "properties": ["dependentExternalExecutableEntityGroup"]
  },
  {
    "operations": {},
    "body": "aRteSource.dependentExternalExecutableEntityGroup",
    "type": "ForIter",
    "constructs": {
      "VariableExpImpl": 1,
      "PropertyCallExpImpl": 1
    },
    "properties": ["dependentExternalExecutableEntityGroup"]
  },
  {
    "operations": {},
    "body": "aGroup.memoryMapping",
    "type": "TemplateInvocationArgument",
    "constructs": {
      "VariableExpImpl": 1,
      "PropertyCallExpImpl": 1
    },
    "properties": ["memoryMapping"]
  },
  {
    "operations": {},
    "body": "aGroup.executableEntity",
    "type": "ForIter",
    "constructs": {
      "VariableExpImpl": 1,
      "PropertyCallExpImpl": 1
    },
    "properties": ["executableEntity"]
  },
  {
    "operations": {},
    "body": "aExecutableEntity",
    "type": "TemplateInvocationArgument",
    "constructs": {"VariableExpImpl": 1},
    "properties": []
  },
  {
    "operations": {},
    "body": "aGroup.memoryMapping",
    "type": "TemplateInvocationArgument",
    "constructs": {
      "VariableExpImpl": 1,
      "PropertyCallExpImpl": 1
    },
    "properties": ["memoryMapping"]
  }
]
