[
  {
    "operations": {
      "toUpperFirst": 1,
      "+": 4
    },
    "body": "'src/'.+(c.package.name).+('/').+(c.name.toUpperFirst()).+('Activity.java')",
    "type": "FileUrl",
    "constructs": {
      "OperationCallExpImpl": 5,
      "VariableExpImpl": 2,
      "StringLiteralExpImpl": 3,
      "PropertyCallExpImpl": 3
    },
    "properties": [
      "name",
      "package"
    ]
  },
  {
    "operations": {},
    "body": "c.package.name",
    "type": "TemplateExpression",
    "constructs": {
      "VariableExpImpl": 1,
      "PropertyCallExpImpl": 2
    },
    "properties": [
      "name",
      "package"
    ]
  },
  {
    "operations": {"toUpperFirst": 1},
    "body": "c.name.toUpperFirst()",
    "type": "TemplateExpression",
    "constructs": {
      "VariableExpImpl": 1,
      "OperationCallExpImpl": 1,
      "PropertyCallExpImpl": 1
    },
    "properties": ["name"]
  },
  {
    "operations": {"toLower": 1},
    "body": "c.name.toLower()",
    "type": "TemplateExpression",
    "constructs": {
      "OperationCallExpImpl": 1,
      "VariableExpImpl": 1,
      "PropertyCallExpImpl": 1
    },
    "properties": ["name"]
  },
  {
    "operations": {},
    "body": "c",
    "type": "TemplateInvocationArgument",
    "constructs": {"VariableExpImpl": 1},
    "properties": []
  },
  {
    "operations": {"toLowerFirst": 1},
    "body": "c.name.toLowerFirst()",
    "type": "TemplateExpression",
    "constructs": {
      "OperationCallExpImpl": 1,
      "VariableExpImpl": 1,
      "PropertyCallExpImpl": 1
    },
    "properties": ["name"]
  },
  {
    "operations": {
      "<>": 1,
      "getAppliedStereotype": 1
    },
    "body": "c.attribute->select(e : Property | e.getAppliedStereotype('profile::EditText').<>(null))",
    "type": "ForIter",
    "constructs": {
      "IteratorExpImpl": 1,
      "VariableExpImpl": 2,
      "OperationCallExpImpl": 2,
      "NullLiteralExpImpl": 1,
      "StringLiteralExpImpl": 1,
      "PropertyCallExpImpl": 1
    },
    "properties": ["attribute"]
  },
  {
    "operations": {"toLowerFirst": 1},
    "body": "c.name.toLowerFirst()",
    "type": "TemplateExpression",
    "constructs": {
      "OperationCallExpImpl": 1,
      "VariableExpImpl": 1,
      "PropertyCallExpImpl": 1
    },
    "properties": ["name"]
  },
  {
    "operations": {},
    "body": "p.name",
    "type": "TemplateExpression",
    "constructs": {
      "VariableExpImpl": 1,
      "PropertyCallExpImpl": 1
    },
    "properties": ["name"]
  },
  {
    "operations": {"toLowerFirst": 1},
    "body": "c.name.toLowerFirst()",
    "type": "TemplateExpression",
    "constructs": {
      "OperationCallExpImpl": 1,
      "VariableExpImpl": 1,
      "PropertyCallExpImpl": 1
    },
    "properties": ["name"]
  },
  {
    "operations": {},
    "body": "p.name",
    "type": "TemplateExpression",
    "constructs": {
      "VariableExpImpl": 1,
      "PropertyCallExpImpl": 1
    },
    "properties": ["name"]
  },
  {
    "operations": {},
    "body": "p.name",
    "type": "TemplateExpression",
    "constructs": {
      "VariableExpImpl": 1,
      "PropertyCallExpImpl": 1
    },
    "properties": ["name"]
  },
  {
    "operations": {"toLowerFirst": 1},
    "body": "c.name.toLowerFirst()",
    "type": "TemplateExpression",
    "constructs": {
      "VariableExpImpl": 1,
      "OperationCallExpImpl": 1,
      "PropertyCallExpImpl": 1
    },
    "properties": ["name"]
  },
  {
    "operations": {},
    "body": "p.name",
    "type": "TemplateExpression",
    "constructs": {
      "VariableExpImpl": 1,
      "PropertyCallExpImpl": 1
    },
    "properties": ["name"]
  },
  {
    "operations": {},
    "body": "c",
    "type": "TemplateInvocationArgument",
    "constructs": {"VariableExpImpl": 1},
    "properties": []
  },
  {
    "operations": {
      "size": 1,
      ">": 1
    },
    "body": "intentResultAssociations->size().>(0)",
    "type": "IfExpression",
    "constructs": {
      "OperationCallExpImpl": 2,
      "VariableExpImpl": 1,
      "IntegerLiteralExpImpl": 1
    },
    "properties": []
  },
  {
    "operations": {
      "toLower": 1,
      "+": 2
    },
    "body": "'res/layout/'.+(c.name.toLower()).+('view.xml')",
    "type": "FileUrl",
    "constructs": {
      "OperationCallExpImpl": 3,
      "VariableExpImpl": 1,
      "StringLiteralExpImpl": 2,
      "PropertyCallExpImpl": 1
    },
    "properties": ["name"]
  },
  {
    "operations": {},
    "body": "c.name",
    "type": "TemplateExpression",
    "constructs": {
      "VariableExpImpl": 1,
      "PropertyCallExpImpl": 1
    },
    "properties": ["name"]
  },
  {
    "operations": {
      "<>": 1,
      "getAppliedStereotype": 1
    },
    "body": "c.attribute->select(e : Property | e.getAppliedStereotype('profile::EditText').<>(null))",
    "type": "ForIter",
    "constructs": {
      "IteratorExpImpl": 1,
      "OperationCallExpImpl": 2,
      "VariableExpImpl": 2,
      "NullLiteralExpImpl": 1,
      "StringLiteralExpImpl": 1,
      "PropertyCallExpImpl": 1
    },
    "properties": ["attribute"]
  },
  {
    "operations": {"toUpperFirst": 1},
    "body": "c.name.toUpperFirst()",
    "type": "TemplateExpression",
    "constructs": {
      "VariableExpImpl": 1,
      "OperationCallExpImpl": 1,
      "PropertyCallExpImpl": 1
    },
    "properties": ["name"]
  },
  {
    "operations": {"toUpperFirst": 1},
    "body": "p.name.toUpperFirst()",
    "type": "TemplateExpression",
    "constructs": {
      "OperationCallExpImpl": 1,
      "VariableExpImpl": 1,
      "PropertyCallExpImpl": 1
    },
    "properties": ["name"]
  },
  {
    "operations": {"toUpperFirst": 1},
    "body": "p.name.toUpperFirst()",
    "type": "TemplateExpression",
    "constructs": {
      "OperationCallExpImpl": 1,
      "VariableExpImpl": 1,
      "PropertyCallExpImpl": 1
    },
    "properties": ["name"]
  },
  {
    "operations": {"toLowerFirst": 1},
    "body": "c.name.toLowerFirst()",
    "type": "TemplateExpression",
    "constructs": {
      "OperationCallExpImpl": 1,
      "VariableExpImpl": 1,
      "PropertyCallExpImpl": 1
    },
    "properties": ["name"]
  },
  {
    "operations": {},
    "body": "p.name",
    "type": "TemplateExpression",
    "constructs": {
      "VariableExpImpl": 1,
      "PropertyCallExpImpl": 1
    },
    "properties": ["name"]
  },
  {
    "operations": {
      "<>": 1,
      "getAppliedStereotype": 1
    },
    "body": "c.attribute->select(e : Property | e.getAppliedStereotype('profile::TextView').<>(null))",
    "type": "ForIter",
    "constructs": {
      "IteratorExpImpl": 1,
      "VariableExpImpl": 2,
      "OperationCallExpImpl": 2,
      "NullLiteralExpImpl": 1,
      "StringLiteralExpImpl": 1,
      "PropertyCallExpImpl": 1
    },
    "properties": ["attribute"]
  },
  {
    "operations": {"toUpperFirst": 1},
    "body": "c.name.toUpperFirst()",
    "type": "TemplateExpression",
    "constructs": {
      "OperationCallExpImpl": 1,
      "VariableExpImpl": 1,
      "PropertyCallExpImpl": 1
    },
    "properties": ["name"]
  },
  {
    "operations": {"toUpperFirst": 1},
    "body": "p.name.toUpperFirst()",
    "type": "TemplateExpression",
    "constructs": {
      "OperationCallExpImpl": 1,
      "VariableExpImpl": 1,
      "PropertyCallExpImpl": 1
    },
    "properties": ["name"]
  },
  {
    "operations": {"toUpperFirst": 1},
    "body": "p.name.toUpperFirst()",
    "type": "TemplateExpression",
    "constructs": {
      "VariableExpImpl": 1,
      "OperationCallExpImpl": 1,
      "PropertyCallExpImpl": 1
    },
    "properties": ["name"]
  },
  {
    "operations": {"toLowerFirst": 1},
    "body": "c.name.toLowerFirst()",
    "type": "TemplateExpression",
    "constructs": {
      "VariableExpImpl": 1,
      "OperationCallExpImpl": 1,
      "PropertyCallExpImpl": 1
    },
    "properties": ["name"]
  },
  {
    "operations": {},
    "body": "p.name",
    "type": "TemplateExpression",
    "constructs": {
      "VariableExpImpl": 1,
      "PropertyCallExpImpl": 1
    },
    "properties": ["name"]
  }
]
