[
  {
    "name": "AttributeType",
    "expressions": [],
    "properties": []
  },
  {
    "name": "Page",
    "expressions": [],
    "properties": [
      "pageElements",
      "title",
      "Form"
    ]
  },
  {
    "name": "Condition",
    "expressions": [],
    "properties": [
      "CompositeCondition",
      "conditionID",
      "type"
    ]
  },
  {
    "name": "Table",
    "expressions": [],
    "properties": ["columns"]
  },
  {
    "name": "Literal",
    "expressions": [],
    "properties": [
      "name",
      "value",
      "Enumeration"
    ]
  },
  {
    "name": "Attribute",
    "expressions": [],
    "properties": [
      "AttributePageElement",
      "Entity",
      "type",
      "mandatory",
      "enumerationType",
      "name",
      "Column",
      "Entity"
    ]
  },
  {
    "name": "RelationshipPageElement",
    "expressions": [],
    "properties": ["editingForm"]
  },
  {
    "name": "PageElement",
    "expressions": [],
    "properties": [
      "Page",
      "elementID",
      "label"
    ]
  },
  {
    "name": "Operators",
    "expressions": [],
    "properties": []
  },
  {
    "name": "Relationship",
    "expressions": [],
    "properties": [
      "opposite",
      "name",
      "Entity",
      "target",
      "lowerBound",
      "upperBound",
      "Relationship"
    ]
  },
  {
    "name": "TextArea",
    "expressions": [],
    "properties": []
  },
  {
    "name": "DateSelectionField",
    "expressions": [],
    "properties": []
  },
  {
    "name": "ConditionType",
    "expressions": [],
    "properties": []
  },
  {
    "name": "AttributePageElement",
    "expressions": [],
    "properties": ["attribute"]
  },
  {
    "name": "TimeSelectionField",
    "expressions": [],
    "properties": []
  },
  {
    "name": "Entity",
    "expressions": [],
    "properties": [
      "Entity",
      "Form",
      "name",
      "Relationship",
      "id",
      "superType",
      "EFML",
      "attributes",
      "relationships"
    ]
  },
  {
    "name": "CompositeCondition",
    "expressions": [],
    "properties": [
      "operator",
      "conditions"
    ]
  },
  {
    "name": "Form",
    "expressions": [],
    "properties": [
      "title",
      "RelationshipPageElement",
      "entity",
      "description",
      "name",
      "pages",
      "EFML",
      "mainForm"
    ]
  },
  {
    "name": "AttributeValueCondition",
    "expressions": [],
    "properties": ["value"]
  },
  {
    "name": "Enumeration",
    "expressions": [],
    "properties": [
      "Attribute",
      "name",
      "literals"
    ]
  },
  {
    "name": "Column",
    "expressions": [],
    "properties": [
      "Table",
      "entityAttribute"
    ]
  },
  {
    "name": "TextField",
    "expressions": [],
    "properties": ["format"]
  },
  {
    "name": "EFML",
    "expressions": [{
      "operations": {"=": 1},
      "name": "",
      "body": "self.forms -> forAll(f | f.mainForm=true)",
      "type": "ConstraintImpl",
      "constructs": {
        "IteratorExpImpl": 1,
        "VariableExpImpl": 2,
        "OperationCallExpImpl": 1,
        "BooleanLiteralExpImpl": 1,
        "PropertyCallExpImpl": 2
      },
      "properties": [
        "forms::EFML::forms",
        "forms::Form::mainForm"
      ]
    }],
    "properties": [
      "entities",
      "forms"
    ]
  },
  {
    "name": "SelectionField",
    "expressions": [],
    "properties": []
  },
  {
    "name": "List",
    "expressions": [],
    "properties": []
  }
]
